{
  "common": {
    "save": "Speichern",
    "activity": "Aktivität",
    "cancel": "Abbrechen",
    "delete": "Löschen",
    "edit": "Bearbeiten",
    "add": "Neu",
    "remove": "Entfernen",
    "confirm": "Bestätigen",
    "back": "Zurück",
    "next": "Nächste",
    "previous": "Vorherige",
    "loading": "Wird geladen...",
    "error": "Fehler",
    "success": "Erfolg",
    "warning": "Warnung",
    "info": "Informationen",
    "yes": "Ja",
    "no": "Nein",
    "ok": "Ok",
    "close": "Schließen",
    "search": "Suchen",
    "filter": "Filtern",
    "sort": "Sortieren",
    "refresh": "Aktualisieren",
    "export": "Exportieren",
    "exportCSV": "CSV exportieren",
    "import": "Importieren",
    "upload": "Hochladen",
    "download": "Download",
    "chatNow": "Jetzt chatten",
    "copy": "Kopieren",
    "paste": "Einfügen",
    "select": "Auswählen",
    "all": "Alle",
    "none": "Keine",
    "actions": "Aktionen",
    "status": "Status",
    "date": "Datum",
    "createdAt": "Erstellt am",
    "time": "Zeit",
    "name": "Name",
    "description": "Beschreibung",
    "type": "Typ",
    "category": "Kategorie",
    "tags": "Tags",
    "language": "Sprache",
    "english": "Englisch",
    "french": "Französisch",
    "german": "Deutsch",
    "spanish": "Spanisch",
    "japanese": "Japanisch",
    "portuguese": "Portugiesisch",
    "italian": "Italienisch",
    "chinese": "Chinesisch",
    "vietnamese": "Vietnamese",
    "show": "Zeigen",
    "hide": "Verstecken",
    "uploadCSVFile": "CSV-Datei hochladen",
    "downloadSampleCSV": "Beispiel CSV herunterladen",
    "acceptsCSV": ".csv-Dateien akzeptieren",
    "countryUnitedStates": "Vereinigte Staaten",
    "countryVietnam": "Vietnam",
    "countryChina": "China",
    "enable": "Aktivieren",
    "disable": "Deaktivieren",
    "paid": "Bezahlt",
    "total": "Gesamt",
    "sent": "Gesendet",
    "scheduled": "Geplant",
    "opened": "Geöffnet",
    "rated": "Bewertet",
    "failed": "Fehler",
    "notSend": "Nicht senden",
    "static": "Statisch",
    "emails": "E-Mails",
    "questions": "Fragen",
    "reviews": "Bewertungen",
    "review": "Überprüfen",
    "learnMoreAbout": "Erfahre mehr über",
    "widgetsSection": "Widgets-Abschnitt",
    "productsSection": "Produkt-Bereich",
    "products": "Produkte",
    "product": "Produkt",
    "reviewsSection": "Rezensionsbereich",
    "questionsSection": "Fragenbereich",
    "emailsSection": "E-Mail-Bereich",
    "updateAndSendEmail": "Update & E-Mail senden",
    "helpful": "Hilfreich:",
    "images": "Bilder",
    "upgradeNow": "Jetzt upgraden",
    "getHelp": "Hilfe erhalten",
    "installNow": "Jetzt installieren"
  },
  "settings": {
    "title": "Einstellungen",
    "annuallyAt": "Jährlich um",
    "monthlyAt": "Monatlich um",
    "profile": "Profil",
    "membership": "Mitgliedschaft",
    "firstName": "Vorname",
    "lastName": "Nachname",
    "email": "E-Mail",
    "username": "Benutzername",
    "adminLanguage": "Adminsprache",
    "timezone": "Zeitzonen",
    "languageAndTimezone": "Sprache und Zeitzone",
    "yourPlan": "Dein Paket",
    "billingCycle": "Abrechnungszyklus",
    "renewalDate": "Erneuerungsdatum",
    "unsubscribe": "Abmelden",
    "editMembership": "Mitgliedschaft bearbeiten",
    "uploadFiles": "Dateien hochladen",
    "unsubscribeFromPlan": "Plan abbestellen?",
    "unsubscribing": "Abmeldung...",
    "yesUnsubscribe": "Ja, Abmelden",
    "unsubscribeWarning": "Sind Sie sicher, dass Sie das Abonnement abbestellen möchten? Sie verlieren den Zugriff auf Premium-Funktionen am Ende Ihres Abrechnungszyklus.",
    "unsubscribeConfirm": "Sind Sie sicher, dass Sie das Abonnement abbestellen möchten?",
    "unsubscribeSuccess": "Sie wurden erfolgreich abgemeldet.",
    "unsubscribeError": "Beim Abmelden ist ein Fehler aufgetreten.",
    "unsubscribeConfirmText": "Sind Sie sicher, dass Sie das Abonnement abbestellen möchten?",
    "unsubscribeSuccessText": "Sie wurden erfolgreich abgemeldet.",
    "unsubscribeErrorText": "Beim Abmelden ist ein Fehler aufgetreten.",
    "CLICK_TO_ACT": "Zum Handeln klicken",
    "FEATURED_POPUP": "Empfohlenes Popup",
    "REVIEWS_PAGE_URL": "Bewertungsseiten-URL",
    "FEATURED_PAGE_URL": "URL der vorgestellten Seite",
    "LAYOUT": "Layout",
    "WIDGET_STYLE": "Widget-Stil",
    "BADGE_ORIENTATION": "Badge-Ausrichtung",
    "SHOW_HEADER": "Header anzeigen",
    "STORE_NAME": "Shopname",
    "IMAGE_HEIGHT": "Bildhöhe",
    "IMAGE_BADGE": "Abzeichen",
    "LABEL_BACKGROUND": "Hintergrund",
    "TEXT_COLOR": "Textfarbe"
  },
  "reviews": {
    "allReviews": "Alle Bewertungen",
    "pendingReviews": "Ausstehende Bewertungen",
    "approvedReviews": "Genehmigte Bewertungen",
    "rejectedReviews": "Abgelehnte Bewertungen",
    "reviewDetails": "Bewertungsdetails",
    "reviewer": "Prüfer",
    "rating": "Bewertung",
    "comment": "Kommentar",
    "approve": "Bestätigen",
    "reject": "Ablehnen",
    "view": "Ansicht",
    "noReviews": "Keine Bewertungen gefunden",
    "exportReviews": "Bewertungen exportieren",
    "bulkActions": {
      "setFeatured": "Empfohlen setzen",
      "unsetFeatured": "Empfohlen entfernen",
      "delete": "Löschen"
    },
    "selectAll": "Alle auswählen",
    "deselectAll": "Alle abwählen",
    "filterByStatus": "Nach Status filtern",
    "filterByRating": "Nach Bewertung filtern",
    "filterByDate": "Nach Datum filtern",
    "searchReviews": "Bewertungen durchsuchen...",
    "reviewCount": "{{count}} Bewertung",
    "reviewCount_plural": "{{count}} Bewertungen",
    "static": "Statisch",
    "average": "Durchschnitt",
    "totalReviews": "Gesamte Bewertungen",
    "unpublish": "Zurückziehen",
    "reviews": "Bewertungen",
    "author": "Autor",
    "content": "Inhalt",
    "comments": "Kommentare",
    "featured": "Empfohlen",
    "publish": "Veröffentlichen",
    "unpublished": "Unpubliziert",
    "published": "Veröffentlicht",
    "removeFeatured": "Empfohlen entfernen",
    "setAsFeatured": "Als Empfohlen festlegen",
    "editReview": "Bewertung bearbeiten",
    "deleteReview": "Bewertung löschen",
    "viewProduct": "Artikel in Ihrem Shop anzeigen",
    "editReviews": "Bewertungen bearbeiten",
    "title": "Titel",
    "images": "Bilder",
    "acceptsImages": "Akzeptiert .gif, .jpg und .png",
    "deleteReviewTitle": "Bewertung löschen?",
    "cannotBeUndone": "Dies kann nicht rückgängig gemacht werden.",
    "deleteAllReviewsTitle": "Alle Bewertungen löschen?",
    "deleting": "Löschen...",
    "deletingReview": "Bewertung wird gelöscht...",
    "saving": "Speichern...",
    "reviewSaved": "Gespeichert",
    "reviewDeleted": "Bewertung gelöscht.",
    "allReviewsDeleted": "Alle Bewertungen erfolgreich gelöscht.",
    "reviewSavedStatus": "Überprüfung gespeichert.",
    "bulkActionSuccess": {
      "show": "Bewertungen erfolgreich angezeigt",
      "hide": "Bewertungen erfolgreich ausgeblendet",
      "feature": "Bewertungen als Sonderartikel festgelegt",
      "unfeature": "Bewertungen nicht als Sonderartikel festgelegt"
    },
    "bulkActionTitles": {
      "show": "{{count}} Bewertungen zu veröffentlichen?",
      "hide": "{{count}} Bewertungen auf unveröffentlicht setzen?",
      "feature": "{{count}} Bewertungen als Feature festlegen?",
      "unfeature": "Funktionierte für {{count}} Bewertungen entfernen?"
    },
    "bulkActionDescriptions": {
      "show": "Setzen Sie diese Bewertungen auf veröffentlicht wird es auf Ihrer Produktseite verfügbar machen.",
      "hide": "Wenn diese Bewertungen auf unveröffentlicht gesetzt werden, werden sie auf Ihrer Produktseite versteckt.",
      "feature": "Wenn Sie diese Bewertungen als Sonderbewertungen einstellen, werden sie auf Ihrer Produktseite hervorgehoben.",
      "unfeature": "Das Zurücksetzen der Funktion wird das Highlight aus diesen Bewertungen entfernen."
    },
    "bulkActionButtons": {
      "show": "Als Veröffentlichung festlegen",
      "hide": "Als unveröffentlicht festlegen",
      "feature": "Als Sonderartikel festlegen",
      "unfeature": "Empfohlen entfernen"
    },
    "promotedBulkActions": {
      "publish": "Veröffentlichen",
      "unpublish": "Zurückziehen"
    },
    "filters": {
      "rating": "Bewertung",
      "type": "Überprüfen",
      "source": "Quelle",
      "star": "Stern",
      "onlyText": "Nur Text",
      "photo": "Foto",
      "aliexpress": "AliExpress",
      "amazon": "Amazonas",
      "etsy": "Etsy",
      "dhgate": "DHgate",
      "walmart": "Walmart",
      "shopee": "Schießen",
      "csv": "CSV",
      "email": "E-Mail"
    },
    "tabs": {
      "all": "Alle",
      "published": "Veröffentlicht",
      "unpublished": "Unpubliziert",
      "featured": "Empfohlen",
      "notFeatured": "Nicht empfohlen"
    },
    "sortOptions": {
      "createdAtAsc": "Erstellt am",
      "createdAtDesc": "Erstellt am",
      "importedAtAsc": "Importiert am",
      "importedAtDesc": "Importiert am"
    },
    "searchPlaceholder": "Suche in allen",
    "moreActions": "Weitere Aktionen",
    "viewOnStore": "Im Shop anzeigen",
    "deleteAllReviews": "Alle Bewertungen löschen",
    "importCSV": "CSV importieren",
    "importReviews": "Bewertungen importieren",
    "reviewsVisible": "Bewertungen sichtbar",
    "reviewsHidden": "Bewertungen versteckt",
    "back": "Zurück",
    "product": "Produkt",
    "repliesList": "Antwortliste",
    "nothingHere": "Nichts hier",
    "noReplies": "Es gibt keine Antworten",
    "leaveComment": "Kommentar hinterlassen...",
    "send": "Senden",
    "replyAdded": "Antwort hinzugefügt.",
    "replySaved": "Antwort gespeichert.",
    "replyDeleted": "Antwort gelöscht.",
    "deletingReply": "Löschen...",
    "savingReply": "Speichern...",
    "shopifyTermsWarning": "Sie dürfen nur die Grammatik korrigieren oder den Inhalt der Rezension klarstellen. Starbewertungen können nicht geändert werden.",
    "shopifyPartnerAgreement": "Shopify Partnerprogramm Vereinbarung",
    "filterLabels": {
      "rating": "Bewertung: {{value}}",
      "type": "Bewertungstyp: {{value}}",
      "source": "Quelle: {{value}}"
    },
    "deleteAllReviewsOfProducts": "Alle Bewertungen von {{count}} Produkten löschen",
    "exportCsv": "CSV exportieren",
    "exportGoogleFeed": "Google Feed exportieren",
    "importing": "Importieren...",
    "importCompleted": "Import abgeschlossen!",
    "importSuccess": "{{count}} Bewertungen erfolgreich importiert.",
    "importErrors": "{{count}} Fehler:",
    "importFailed": "Import fehlgeschlagen.",
    "csvFormatNote": "Bitte stellen Sie sicher, dass Ihre CSV-Datei dem erforderlichen Format folgt:",
    "productHandleRequired": "product_handle (erforderlich)",
    "ratingRequired": "Bewertung (benötigte Zahl)",
    "emailRequired": "E-Mail (benötigte, gültige E-Mail)",
    "createdAtOptional": "created_at (optional)",
    "averageTooltipProduct": "Durchschnittliche Bewertung des Produkts",
    "averageTooltipShop": "Durchschnittliche Bewertung des Shops",
    "totalTooltip": "Gesamtzahl der Bewertungen",
    "totalWithPhotoTooltip": "Gesamtzahl der Bewertungen mit Fotos",
    "totalWithVideoTooltip": "Gesamtzahl der Bewertungen mit Videos",
    "totalWithTextTooltip": "Gesamtzahl der Bewertungen mit Text",
    "totalWithAnswerTooltip": "Gesamtzahl der Bewertungen mit Antworten",
    "totalWithLikeTooltip": "Gesamtzahl der Bewertungen mit Gefällt mir",
    "totalReviewsTooltip": "Gesamtzahl der Bewertungen",
    "unpublishTooltip": "Anzahl unveröffentlichter Bewertungen",
    "totalReviewsTooltipProduct": "Gesamtzahl der Bewertungen für das Produkt",
    "unpublishTooltipProduct": "Anzahl unveröffentlichter Bewertungen für das Produkt",
    "reasonEditReview": "Bitte geben Sie einen Grund für Ihre Bearbeitung an.",
    "reasonEditReviewPlaceholder": "Grund eingeben",
    "reasonEditReviewHelpText": "Wir senden Ihnen auch eine E-Mail an den ursprünglichen Überprüfer, um Ihre vorgeschlagenen Änderungen zu bestätigen.",
    "starRatingsFixed": "Sternbewertungen sind fixiert und können nicht geändert werden."
  },
  "products": {
    "title": "Produkte",
    "allProducts": "Alle Produkte",
    "productDetails": "Produktdetails",
    "productName": "Produktname",
    "productId": "Produkt-ID",
    "sku": "SKU",
    "price": "Preis",
    "brand": "Marke",
    "images": "Bilder",
    "variants": "Varianten",
    "inventory": "Inventar",
    "active": "Aktiv",
    "inactive": "Inaktiv",
    "draft": "Entwurf",
    "published": "Veröffentlicht",
    "importProducts": "Produkte importieren",
    "exportProducts": "Produkte exportieren",
    "noProducts": "Keine Produkte gefunden",
    "productCount": "{{count}} Produkt",
    "productCount_plural": "{{count}} Produkte",
    "importSettings": "Import-Einstellungen",
    "importFromCSV": "Import aus CSV",
    "importFromAliExpress": "Von AliExpress importieren",
    "importFromAmazon": "Aus Amazon importieren",
    "importFromEtsy": "Aus Etsy importieren",
    "productStatus": "Produktstatus"
  },
  "questions": {
    "title": "Fragen",
    "allQuestions": "Alle Fragen",
    "questionDetails": "Fragendetails",
    "question": "Frage",
    "answer": "Antwort",
    "asker": "Asker",
    "respondent": "Befragte",
    "pending": "Ausstehend",
    "answered": "Beantwortet",
    "rejected": "Abgelehnt",
    "approve": "Bestätigen",
    "reject": "Ablehnen",
    "view": "Ansicht",
    "addQuestion": "Frage hinzufügen",
    "editQuestion": "Frage bearbeiten",
    "deleteQuestion": "Frage löschen",
    "importQuestions": "Fragen importieren",
    "exportQuestions": "Fragen exportieren",
    "bulkActions": "Massenaktionen",
    "selectAll": "Alle auswählen",
    "deselectAll": "Alle abwählen",
    "filterByStatus": "Nach Status filtern",
    "filterByDate": "Nach Datum filtern",
    "searchQuestions": "Fragen suchen...",
    "noQuestions": "Keine Fragen gefunden",
    "questionCount": "{{count}} Frage",
    "questionCount_plural": "{{count}} Fragen",
    "importFromCSV": "Import aus CSV",
    "questionType": "Fragentyp",
    "general": "Allgemein",
    "productSpecific": "Produktspezifisch",
    "customerService": "Kundendienst",
    "technical": "Technisch",
    "author": "Autor",
    "publish": "Veröffentlichen",
    "unpublish": "Zurückziehen",
    "published": "Veröffentlicht",
    "unpublished": "Zurückziehen",
    "like": "Möge",
    "dislike": "Dislike",
    "likes": "Gefällt",
    "dislikes": "Dislikes",
    "hasAnswer": "Hat Antwort",
    "comments": "Kommentare",
    "send": "Senden",
    "leaveAnswer": "Antwort hinterlassen...",
    "nothingHere": "Nichts hier",
    "noAnswers": "Es gibt keine Antworten",
    "areYouSureDelete": "Sind Sie sicher, dass Sie diese Antwort löschen möchten?",
    "sureDeleteAnswer": "Sind Sie sicher, dass Sie diese Antwort löschen möchten?",
    "yesDelete": "Ja, löschen",
    "updating": "Frage wird aktualisiert...",
    "questionSaved": "Frage gespeichert.",
    "questionDeleted": "Frage gelöscht.",
    "questionsDeleted": "Fragen gelöscht.",
    "answerSaved": "Antwort gespeichert",
    "answerDeleted": "Antwort gelöscht",
    "questionsUpdated": "Fragen aktualisiert.",
    "failedToUpdate": "Fehler beim Aktualisieren der Frage",
    "failedToDelete": "Fehler beim Löschen der Frage",
    "deleteQuestionTitle": "Frage löschen",
    "deleteQuestionsTitle": "{{count}} Fragen löschen",
    "cannotBeUndone": "Dies kann nicht rückgängig gemacht werden.",
    "publishQuestionsTitle": "{{count}} Fragen veröffentlichen",
    "unpublishQuestionsTitle": "{{count}} Fragen zurückziehen",
    "sureToPublish": "Sind Sie sicher, dass Sie diese Fragen veröffentlichen möchten?",
    "sureToUnpublish": "Sind Sie sicher, dass Sie diese Fragen zurückziehen möchten?",
    "searchPlaceholder": "In Fragen und Autoren suchen",
    "createdAt": "Erstellt am",
    "authorSort": "Autor",
    "answersList": "Antwortliste",
    "editQuestionTitle": "Fragen bearbeiten",
    "questionRequired": "Frage ist erforderlich",
    "authorRequired": "Autor ist erforderlich",
    "fileUploadedInfo": "Datei hochgeladen! Jetzt können Sie Fragen importieren.",
    "importing": "Importieren...",
    "importSuccess": "Import erfolgreich!",
    "importFailed": "Import fehlgeschlagen",
    "fileSizeLimit": "Dateigröße überschreitet 1MB Limit",
    "csvMissingFields": "CSV fehlende Pflichtfelder: product_handle, Autor, E-Mail, Frage",
    "csvInvalidRows": "CSV hat {{count}} ungültige Zeile(n). Jede Zeile muss alle erforderlichen Felder haben.",
    "csvParseError": "CSV parse error: {{message}}",
    "cannotReadFile": "Datei kann nicht gelesen werden",
    "uploadFailed": "Upload fehlgeschlagen: {{message}}",
    "rowsFailedToImport": "{{count}} Zeile(n) konnten nicht importiert werden:",
    "row": "Zeile",
    "upgradeBanner": {
      "title": "Upgrade um Q&A Funktionen freizuschalten",
      "desc": "Die Funktion Frage und Antwort steht ausschließlich für kostenpflichtige Pläne zur Verfügung. Aktualisieren Sie jetzt Ihr Konto, um Fragen zu beantworten und sich direkt mit Ihren Kunden in Verbindung zu setzen, um Trust aufzubauen und Konversionen anzutreiben.",
      "upgradeNow": "Jetzt upgraden",
      "learnMore": "Mehr erfahren"
    },
    "titleTooltip": "Anzahl der Fragen im Shop",
    "answeredTooltip": "Anzahl der Antworten im Shop",
    "likeTooltip": "Anzahl der Likes im Shop",
    "dislikeTooltip": "Anzahl der Ungefallen im Shop",
    "questionsTooltipProduct": "Anzahl der Fragen zum Produkt",
    "answeredTooltipProduct": "Anzahl der Antworten auf das Produkt",
    "likeTooltipProduct": "Anzahl der Gefällt mir",
    "dislikeTooltipProduct": "Anzahl der Ungefallen auf dem Produkt",
    "importCSVNotAvailable": "Import CSV nicht verfügbar",
    "importCSVNotAvailableDescription": "Import CSV unterstützt den kostenlosen Plan nicht. Bitte upgraden Sie auf ein kostenpflichtiges Paket, um diese Funktion zu nutzen."
  },
  "widgets": {
    "title": "Widgets",
    "allWidgets": "Alle Widgets",
    "widgetDetails": "Widget-Details",
    "widgetName": "Widget-Name",
    "widgetType": "Widget-Typ",
    "widgetId": "Widget-ID",
    "active": "Aktiv",
    "inactive": "Inaktiv",
    "draft": "Entwurf",
    "published": "Veröffentlicht",
    "importWidgets": "Widgets importieren",
    "exportWidgets": "Widgets exportieren",
    "noWidgets": "Keine Widgets gefunden",
    "widgetCount": "{{count}} Widget",
    "widgetCount_plural": "{{count}} Widgets",
    "enableAppEmbed": "App-Einbettung aktivieren",
    "moreDetails": "Mehr Details",
    "customize": "Anpassen",
    "addNow": "Jetzt hinzufügen",
    "enableNow": "Jetzt aktivieren",
    "heading": "Überschrift",
    "rateList": "Bewertungsliste",
    "reviewImagesList": "Bilderliste überprüfen",
    "showingText": "Text anzeigen",
    "customizeWidgetTexts": "Widget-Texte anpassen",
    "general": "Allgemein",
    "layout": "Layout",
    "color": "Farbe",
    "typography": "Typographie",
    "sections": "Abschnitte",
    "formatting": "Formatierung",
    "author": "Autor",
    "media": "Medien",
    "stars": "Sterne",
    "widgetStyle": "Widget-Stil",
    "language": "Sprache",
    "preview": "Vorschau",
    "reviewApproval": "Freigabe überprüfen",
    "lazyLoad": "Langsame Last",
    "sortBy": "Sortieren nach",
    "reviewsPerPage": "Bewertungen pro Seite",
    "loadReviews": "Bewertungen laden",
    "collectionShowing": "Sammlung zeigt",
    "hideEmptyRatings": "Leere Bewertungen ausblenden",
    "questionApproval": "Freigabe der Frage",
    "answerApproval": "Genehmigung beantworten",
    "questionsPerPage": "Fragen pro Seite",
    "theme": "Thema",
    "removeBorderInReviewItem": "Rand in Rezensions-Element entfernen",
    "displayOneColumnReviewOnMobile": "Eine Spaltenüberprüfung auf dem Handy anzeigen",
    "autoplay": "Autoplay",
    "autoPlaySpeedInMilliseconds": "Automatische Wiedergabegeschwindigkeit in Millisekunden",
    "autoHeight": "Automatische Höhe",
    "headerLayout": "Header-Layout",
    "ryviuSidebarWidget": "Ryviu Seitenleisten-Widget",
    "offsetSidebar": "Versatz-Sidebar",
    "popUp": "Popup",
    "position": "Position",
    "background": "Hintergrund",
    "activeColor": "Aktiv",
    "inactiveColor": "Inaktiv",
    "colorTitle": "Farbtitel",
    "backgroundButton": "Hintergrund-Button",
    "colorButton": "Farbschaltfläche",
    "mainColor": "Hauptfarbe",
    "baseSize": "Grundgröße",
    "fontFamily": "Schriftfamilie",
    "header": "Kopfzeile",
    "filterAndSortReviews": "Rezensionen filtern & sortieren",
    "writeReview": "Bewertung schreiben",
    "reviewerDetails": "Reviewer Details",
    "reviewDetails": "Bewertungsdetails",
    "reviewContentDisplay": "Inhaltsanzeige überprüfen",
    "reviewEngagement": "Rezension",
    "popupImage": "Popup-Bild",
    "featuredItem": "Empfohlene Artikel",
    "writeAReviewForm": "Bewertungsformular schreiben",
    "multipleImagesOnReview": "Mehrere Bilder werden geprüft",
    "autoHeightImages": "Auto Höhe Bilder",
    "effectsWhenHoveringImages": "Effekte beim Herfahren von Bildern",
    "yourLanguage": "Ihre Sprache",
    "reviewsWidget": "Bewertungs-Widget",
    "button": "Button",
    "verifyIcon": "Symbol überprüfen",
    "popup": "Popup",
    "form": "Formular",
    "avatar": "Avatar",
    "filter": "Filtern",
    "sortByCheckbox": "Sortieren nach",
    "writeAReview": "Bewertung schreiben",
    "uploadVideo": "Video hochladen",
    "authorName": "Name des Autors",
    "reviewImages": "Bilder überprüfen",
    "verifiedIcon": "Verifiziertes Symbol",
    "dateTime": "Datumszeit",
    "reviewTitle": "Rezensionstitel",
    "comment": "Kommentar",
    "fullContent": "Vollständiger Inhalt",
    "reaction": "Reaktion",
    "reviewOnPopupImage": "Auf Popup-Bild überprüfen",
    "productInfo": "Produktinfo",
    "customerNameFormat": "Kundennamenformat",
    "dateFormat": "Datumsformat",
    "randomColor": "Zufällige Farbe",
    "showOnlyTextAvatars": "Nur Text-Avatare anzeigen",
    "previewSpecificSettingsNote": "Vorschau-spezifische Einstellungen wirken sich nicht auf das Farbdisplay in Ihrem Shop aus.",
    "latest": "Neueste",
    "oldest": "Älteste",
    "highestRating": "Höchste Bewertung",
    "lowestRating": "Niedrigste Bewertung",
    "loadMoreButton": "Weitere Schaltfläche laden",
    "infiniteScroll": "Unendliche Schriftrolle",
    "mostHelpful": "Am hilfreich",
    "newest": "Neueste",
    "masonry": "Mauerwerk",
    "disabled": "Deaktiviert",
    "ms": "M",
    "helpText": {
      "reviewApproval": "Genehmigung anfordern, bevor Bewertungen veröffentlicht werden",
      "lazyLoad": "Bewertungen laden, wenn sie in die Ansicht kommen",
      "collectionShowing": "Sternbewertung auf Sammlungsseite anzeigen",
      "hideEmptyRatings": "Sternbewertungen nicht auf der Sammlungsseite anzeigen, wenn keine Bewertungen vorhanden sind",
      "questionApproval": "Genehmigung erforderlich bevor Fragen veröffentlicht werden",
      "answerApproval": "Genehmigung erforderlich bevor Antworten veröffentlicht werden"
    },
    "questionApprovalHelp": "Q&A zur Anzeige auf der Seite freigeben",
    "questionsPerPageHelp": "Die maximale Anzahl von Fragen pro Seite ist 20",
    "buttonBackground": "Hintergrund der Schaltfläche",
    "buttonColor": "Schaltflächenfarbe",
    "createdTime": "Erstellte Zeit",
    "askTheCommunity": "Frage die Community",
    "answer": "Antwort",
    "votes": "Abstimmungen",
    "askCommunityBlock": "Community-Block fragen",
    "askCommunity": "Community fragen",
    "textAskButton": "Text-Eingabe-Button",
    "headerSection": "Header-Bereich",
    "headerTitle": "Titel der Kopfzeile",
    "customerPage": "Kundenseite",
    "searchBar": "Suchleiste",
    "placeholderSearchInput": "Platzhalter-Sucheingabe",
    "noQuestion": "Keine Frage",
    "questionsNotFound": "Keine Fragen gefunden",
    "showing": "Anzeigen",
    "of": "von",
    "question": "Frage",
    "questions": "Fragen",
    "questionItem": "Fragen-Element",
    "vote": "Abstimmungen",
    "total": "Gesamt",
    "answers": "Antworten",
    "seeAll": "Alle ansehen",
    "answerItem": "Antwort Element",
    "shopOwner": "Shopbesitzer",
    "questionForm": "Frageformular",
    "titleForm": "Titelformular",
    "titleFormAskQuestion": "Titelformular Frage stellen",
    "descriptionForm": "Beschreibungsformular",
    "nameField": "Namensfeld",
    "yourName": "Ihr Name",
    "namePlaceholder": "Textfeldname Platzhalter",
    "emailField": "E-Mail-Feld",
    "yourEmail": "Ihre E-Mail",
    "emailPlaceholder": "Textfeld E-Mail-Platzhalter",
    "questionField": "Fragenfeld",
    "yourQuestion": "Ihre Frage",
    "questionPlaceholder": "Platzhalter für Textfelder",
    "sendAQuestion": "Frage senden",
    "successMessage": "Erfolgsmeldung",
    "sendQuestionSuccess": "Frage erfolgreich gesendet",
    "errorMessage": "Fehlermeldung",
    "sendQuestionError": "Fehler bei der Frage senden",
    "answerForm": "Antwort-Formular",
    "answerTitleForm": "Titelformular der Antwort",
    "questionLabelForm": "Fragenbezeichnungsformular",
    "answerField": "Antwortfeld",
    "yourAnswer": "Ihre Antwort",
    "answerPlaceholder": "Platzhalter für Textfeld",
    "submitAnswer": "Antwort senden",
    "sendReplySuccess": "Antwort erfolgreich gesendet",
    "sendReplyError": "Antwortfehler senden",
    "textErrorOnAnswerForm": "Textfehler im Antwortformular",
    "answersList": "Antwortliste",
    "on": "Über",
    "error": {
      "maxValue50": "Der maximale Wert ist 50"
    },
    "leftSide": "Linke Seite",
    "rightSide": "Rechte Seite",
    "withReviews": "Mit Bewertungen",
    "withoutReviews": "Ohne Bewertungen",
    "withQuestions": "Mit Fragen",
    "withoutQuestions": "Ohne Fragen",
    "featuredMasonry": "Empfohlenes Mauerwerk",
    "featuredCarousel": "Empfohlene Karussell",
    "showPreviewWithReviews": "Vorschau mit Bewertungen anzeigen",
    "showPreviewWithoutReviews": "Vorschau ohne Bewertungen anzeigen",
    "chooseWidgetLanguageForReviews": "Wähle die Widget-Sprache für Rezensionen",
    "chooseWidgetLanguageForQuestions": "Wählen Sie die Widget-Sprache für Fragen",
    "reviewTotalTexts": "rezensionen",
    "border": "Border",
    "padding": "Padding",
    "style": "Stil",
    "size": "Größe",
    "none": "Keine",
    "dotted": "Gepunktet",
    "dashed": "Gestattet",
    "solid": "Solid",
    "double": "Doppelt",
    "groove": "Groove",
    "ridge": "Ridge",
    "inset": "Inset",
    "outset": "Beginn",
    "top": "Oben",
    "right": "Rechts",
    "bottom": "Unten",
    "left": "Links",
    "ratingDefault": "Bewertung Standard",
    "ratingDefaultForWriteForm": "Bewertung der Standardwerte für das Schreibformular.",
    "icon": "Symbol",
    "resizeImageToFitContainer": "Ändern Sie die Größe des Bildes an den Behälter.",
    "cover": "Cover",
    "contain": "Enthält",
    "headerV1": "HeaderV1",
    "enable": "Aktivieren",
    "bottomLeft": "Unten links",
    "horizontal": "Horizontal",
    "fifty": "50",
    "configureCustomerNameFormat": "Konfigurieren Sie das Anzeigeformat für Kundennamen in Bewertungen",
    "monthDdYyyy": "Monat Td, jjjj",
    "mthYyyy": "Mth jjjj",
    "ddMmYy": "dd/mm/jj",
    "dMyyyy": "d/m/jjjj",
    "mmDdYyyy": "mm/tt/jjjj",
    "ddMmYyyy": "dd.mm.jjjj",
    "yyyyMmD": "jjjjj-mm-dd",
    "oneYearAgo": "Vor 1 Jahr",
    "topRight": "Oben rechts",
    "topLeft": "Oben links",
    "bottomRight": "Unten rechts",
    "center": "Zentriert",
    "vertical": "Vertikal",
    "modern": "Modern",
    "widgets": {
      "productReviews": {
        "title": "Produktbewertungen",
        "description": "Showcase detaillierte Kundenbewertungen auf Ihren Produktseiten, um Vertrauen zu schaffen und die Konvertierungsraten zu verbessern."
      },
      "totalRatings": {
        "title": "Gesamte Bewertungen",
        "description": "Zeigen Sie die gesamte Produktbewertungszusammenfassung auf Ihren Produkt- und Sammlungsseiten für schnelle Kundeneinsichten."
      },
      "featuredReviews": {
        "title": "Empfohlene Bewertungen hervorheben",
        "description": "Zeigen Sie ausgewählte Kundenbewertungen auf jedem Abschnitt Ihrer Website an, um das effektivste Feedback zu unterstreichen und Glaubwürdigkeit zu schaffen."
      },
      "quickAccess": {
        "title": "Schnellzugriffsknopf",
        "description": "Bieten Sie sofortigen Zugriff auf vorgestellte Bewertungen mit einem speziellen Button auf jedem Abschnitt Ihrer Website."
      },
      "realtimeAlerts": {
        "title": "Echtzeitbewertungs-Warnungen",
        "description": "Benachrichtigen Sie Kunden sofort über neue Produktbewertungen mit einem Popup-Auslöser."
      },
      "reviewBadge": {
        "title": "Bewertungsabzeichen",
        "description": "Um das Vertrauen und die Sichtbarkeit zu steigern, fügen Sie ein Abzeichen hinzu, das die Bewertung Ihres Produkts in jedem Abschnitt Ihrer Website anzeigt."
      },
      "qaSection": {
        "title": "Kunden-F&A-Abschnitt",
        "description": "Kunden können Fragen stellen und Antworten direkt auf Ihren Produktseiten einsehen und so das Kundenengagement verbessern."
      }
    },
    "banner": {
      "title": "Du musst Ryviu-Kern zu deinem Theme hinzufügen!",
      "description": "Um die Ryviu-Funktionen und Einstellungen in Ihrem Shop voll nutzen zu können, aktivieren Sie bitte die Ryviu-App. Klicken Sie unten auf die Schaltfläche 'App einbinden aktivieren' und klicken Sie dann auf Speichern."
    }
  },
  "emails": {
    "title": "E-Mail-Abonnements",
    "emailAutomation": "Email automation",
    "emailNotification": "E-Mail-Benachrichtigung",
    "email": "E-Mail",
    "queueStatus": "Warteschlange Status",
    "orderId": "Bestell-ID",
    "readAt": "Lesen am",
    "createdAt": "Erstellt am",
    "sendEmail": "E-Mail senden",
    "deleteSelected": "Ausgewählte löschen",
    "unverified": "Nicht verifiziert",
    "pending": "Ausstehend",
    "sent": "Gesendet",
    "failed": "Fehler",
    "unknown": "Unbekannt",
    "waiting": "Warten",
    "scheduled": "Geplant",
    "cancelled": "Abgebrochen",
    "notRead": "Nicht gelesen",
    "pleaseSelectEmail": "Bitte wählen Sie mindestens eine E-Mail",
    "emailsDeletedSuccess": "E-Mails erfolgreich gelöscht",
    "emailsSentSuccess": "E-Mails erfolgreich gesendet",
    "errorDeletingEmails": "Fehler beim Löschen der E-Mails",
    "errorSendingEmails": "Fehler beim Senden von E-Mails",
    "singular": "email",
    "plural": "eMails",
    "deletingEmail": "E-Mail wird gelöscht...",
    "deleteEmails": "E-Mails löschen",
    "deleteEmail": "E-Mail löschen",
    "totalTooltip": "Die Gesamtzahl der E-Mails.",
    "sentTooltip": "Die Gesamtzahl der gesendeten E-Mails.",
    "scheduledTooltip": "Die Gesamtzahl der geplanten E-Mails.",
    "openedTooltip": "Die Gesamtzahl der geöffneten E-Mails.",
    "ratedTooltip": "Die Gesamtzahl der bewerteten E-Mails.",
    "failedTooltip": "Die Gesamtzahl der fehlgeschlagenen E-Mails.",
    "notSendTooltip": "Die Gesamtzahl der abgebrochenen E-Mails.",
    "upgradeBanner": {
      "title": "Upgrade auf Entsperren von E-Mail-Funktionen",
      "desc": "E-Mail-Versand ist exklusiv für kostenpflichtige Pläne verfügbar. Aktualisieren Sie jetzt Ihr Konto, um E-Mails direkt aus der App zu versenden und Ihr Kundenengagement mühelos zu verbessern.",
      "upgradeNow": "Jetzt upgraden",
      "learnMore": "Mehr erfahren"
    }
  },
  "dashboard": {
    "title": "Dashboard",
    "overview": "Übersicht",
    "statistics": "Statistiken",
    "recentActivity": "Letzte Aktivität",
    "quickActions": "Schnelle Aktionen",
    "totalReviews": "Gesamte Bewertungen",
    "totalProducts": "Produkte insgesamt",
    "totalQuestions": "Gesamte Fragen",
    "totalWidgets": "Gesamte Widgets",
    "pendingReviews": "Ausstehende Bewertungen",
    "pendingQuestions": "Ausstehende Fragen",
    "recentReviews": "Neueste Bewertungen",
    "recentQuestions": "Letzte Fragen",
    "topProducts": "Top Produkte",
    "performance": "Leistung",
    "analytics": "Analytik",
    "reports": "Berichte",
    "insights": "Einblicke",
    "trends": "Trends",
    "growth": "Wachstum",
    "conversion": "Konvertierung",
    "engagement": "Engagement",
    "satisfaction": "Zufriedenheit",
    "rating": "Bewertung",
    "averageRating": "Durchschnittliche Bewertung",
    "responseRate": "Antwortrate",
    "responseTime": "Antwortzeit",
    "customerSatisfaction": "Kundenzufriedenheit",
    "productPerformance": "Produkt-Leistung",
    "reviewPerformance": "Bewertungsleistung",
    "questionPerformance": "Fragenleistung",
    "static": "Statisch",
    "sales": "Verkäufe",
    "reviews": "Bewertungen",
    "questions": "Fragen",
    "orders": "Bestellungen",
    "emails": "E-Mails",
    "reviewsTooltip": "Die Gesamtzahl der Bewertungen",
    "questionsTooltip": "Die Gesamtzahl der Fragen",
    "emailsTooltip": "Gesamtzahl der E-Mails",
    "needHelp": "Brauchst du Hilfe?",
    "liveChat": "Live-Chat",
    "liveChatContent": "Wir sind von Montag bis Freitag 8 Uhr (GMT+7) erhältlich.",
    "emailSupport": "E-Mail Support",
    "emailSupportContent": "Ihre E-Mail wird in der Regel innerhalb von 12-24 Stunden adressiert.",
    "emailUs": "E-Mail uns",
    "helpCenter": "Hilfe-Center",
    "helpCenterContent": "Schauen Sie sich unsere Schritt-für-Schritt Anleitungen und Artikel zur Fehlerbehebung an.",
    "ourDocument": "Unser Dokument",
    "whatNewsTitle": "Passen Sie Ihr Bewertungs-Widget an.",
    "whatNewsDescription": "Lernen Sie, wie Sie mühelos das Layout Ihres Review-Widgets bearbeiten und personalisieren können. Passen Sie die Stile, Schriften und Farben an das Design und die Marke Ihres Shops an. Folgen Sie unserer Schritt-für-Schritt-Anleitung, um Ihr Widget perfekt für Ihre Kunden aussehen zu lassen.",
    "learnMore": "Mehr erfahren",
    "recommendedApps": "Empfohlene Apps",
    "retonContent": "Belohnung der Treue mit Punkten, Rabatten und exklusiven VIP-Prämien.",
    "ryviuContent": "Importieren Sie Amazon Produkte in Ihren Shopify Shop.",
    "lookfyContent": "Die ultimative Lösung für die Erstellung fesselnder Lookbooks und Produktgalerien.",
    "annifyContent": "Kontaktieren Sie Kunden sofort mit Eye-Catching Announcement Bars.",
    "reviewed": "Überprüft",
    "newQuestion": "Neue Frage",
    "likedReview": "Gefällt Bewertung",
    "dislikedReview": "Bewertung nicht gefällt",
    "replied": "Beantwortet",
    "likedQuestion": "Gefallene Frage",
    "dislikedQuestion": "Frage nicht gefällt",
    "liked": "Gefällt",
    "disliked": "Ungefällt"
  },
  "integrations": {
    "title": "Shopify App Integration",
    "description": "Konversionsrate bei Verwendung mit integrierter App erhöhen",
    "totalApps": "Gesamte {{count}} Shopify Apps",
    "addIntegration": "Integrationsanfrage",
    "descriptions": {
      "ecomposer": "Erstelle Landingpages, Startseiten, Produkt, Sammlungsseiten, etc. die konversionsfokussiert werden",
      "lookify": "Die ultimative Lösung für die Erstellung fesselnder Lookbooks und Produktgalerien.",
      "cross-sell-upsell": "Laufen Sie den Verkauf mit maßgeschneiderten Cross-Sells, Upsells, Pop-ups & Bundles in 8 strategischen Seiten in Ihrem Shopify Shop!",
      "easy-tabs": "Shopify Produktseiten-Registerkarten. Organisieren Sie Produktbeschreibungen, Rezensionen und Größen in proaktiven Tabs.",
      "searchpie": "Erweitern Sie Verkäufe, Site-Ansicht & Such-Rankings mit einem umfangreichen Auto-SEO-Tool.",
      "frequently-bought": "Bundle-Produkte und entfesseln die Kraft des Verkaufs mit personalisierten Empfehlungen und Rabatten.",
      "also-bought": "Premium-Produktempfehlungen zur Steigerung Ihres Umsatzes durch Cross-Selling und Produktentdeckung.",
      "agile-theme": "Top Shopify Theme für elegantes Design, schnelle Performance und effektive Konvertierungswerkzeuge.",
      "json-ld": "Optimieren Sie Ihren SEO-Traffic, indem Sie Ihre Bewertungen, Preise und Geschäftsdaten in den Suchergebnissen hervorheben.",
      "foxify": "Impact Vertrieb, Kosten & Profit auf einmal mit 80+ High-Converting Designs & Advanced Analytics.",
      "lantern": "Erstellen Sie Quizs, die Fenstereinkäufer in zuversichtliche Käufer verwandeln. Buchen Sie eine KOSTENLOSE Quizberatung.",
      "zeno": "Erstellen Sie einfach Seiten und Theme-Sektionen, die Ihren Shop hervorheben und steigern Sie Ihren Umsatz.",
      "beae": "Bauen Sie Flexible Produkt, Sammlung, Homepage, Landing, Kontakt. Kostenlos zu installieren.",
      "bss-labels": "Führen Sie einen hochkonvertierenden Shop mit Trust Labels & Abzeichen.",
      "pagefly": "Erstellen Sie Verkaufslandung, Produktseite für Ferienzeit.",
      "flash-search": "AI powered Search & Filter, Merchandising, Analytics, OS 2.0",
      "product-filter": "Erweiterte Produktfilter & Smart Search für hohe Verkäufe",
      "sales-popup": "Boost Sales Popup Einkäufe & Neuaufträge für Social Proof",
      "neat-theme": "Maßgeschneidert für visuelle Storytelling Marken mit einfachen Anpassungs- und Merchandising-Funktionen.",
      "qikify": "Verkaufs-Popup, soziale Sicherheit, Newsletter-Popup, Verkaufs-Benachrichtigung",
      "veda": "Erschaffen Sie mühelos atemberaubende & vertriebsfördernde Seiten, die die Besucher mit Null-Codierung beschäftigen.",
      "parcel-panel": "Automatische Synchronisation, Tracking & Update, Marken-Tracking-Seite, Versand-Benachrichtigungen, Up-Sell.",
      "seo-optimizer": "SEO-Booster, Alt-Text, Meta-Tags, Pagespeed, Expertendienst",
      "layouthub": "Landing, Produkt und Blog Seiten in weniger als 10 Minuten erstellen",
      "ava-email": "SMS, E-Mail-Marketing, Popup, Klaviyo, Privat, Mailchimp alt",
      "gempages": "GemPages: CRO Page builder with Sales Funnel to convert."
    }
  },
  "startGuide": {
    "title": "Anleitung starten",
    "description": "Verwenden Sie diesen personalisierten Leitfaden um Ihren Shop zum Laufen zu bringen.",
    "tasksCompleted": "{{completed}} von {{total}} erledigten Aufgaben",
    "dismiss": "Verwerfen",
    "markAsDone": "Als erledigt markieren",
    "markAsNotDone": "Als nicht erledigt markieren",
    "steps": {
      "display": {
        "title": "Anzuzeigen",
        "description": "Fügen Sie Ryviu zu Ihrem Theme Ryviu Widgets hinzu, aktivieren Sie den Ryviu Kern in Ihren Theme-Einstellungen. Klicken Sie auf 'Jetzt hinzufügen', dann 'Speichern', und besuchen Sie diese Seite erneut, um die Aktivierung zu bestätigen.",
        "addNow": "Jetzt hinzufügen",
        "check": "Prüfen"
      },
      "showing": {
        "title": "Zeige Ryviu Widgets",
        "description": "Um die Ryviu-Widgets anzuzeigen, navigieren Sie einfach zur Widgets-Seite und folgen Sie den Anweisungen.",
        "widgetsPage": "Widgets-Seite"
      },
      "pickPlan": {
        "title": "Wähle einen Plan",
        "description": "Mit verschiedenen Support-Paketen können Sie Ihren Kontoplan so ändern, dass er den Bedürfnissen Ihres Shops besser entspricht.",
        "moreDetails": "Mehr Details"
      }
    }
  },
  "menu": {
    "home": "Zuhause",
    "products": "Produkte",
    "reviews": "Bewertungen",
    "emails": "E-Mails",
    "questions": "Q&A",
    "widgets": "Widgets",
    "partners": "Partner",
    "pricing": "Preis",
    "settings": "Einstellungen"
  },
  "subscription": {
    "title": "Wählen Sie einen Plan",
    "currentSubscription": "Aktuelles Abonnement",
    "currentPlanMessage": "Sie sind derzeit auf dem {{planName}} Paket.",
    "monthly": "Monatlich",
    "annually": "Jährlich",
    "save25Percent": "-25%",
    "confirmPlan": "Bestätige dein Paket",
    "billingCycle": "Abrechnungszyklus",
    "billingCycleDescription": "Wählen Sie, wie oft Sie abgerechnet werden möchten. Sie können jederzeit stornieren.",
    "monthlyBilling": "Monatlich",
    "yearlyBilling": "Jährlich",
    "payMonthly": "{{price}}/ Monat bezahlen",
    "payYearly": "{{price}}/Monat - zahlen {{yearlyPrice}} ({{monthlyPrice}} × 12 Monate)",
    "saveAmount": "{{amount}} speichern",
    "billedEvery30Days": "alle 30 Tage abgerechnet",
    "discount": "Rabatt",
    "enterDiscountCode": "Rabattcode eingeben",
    "apply": "Anwenden",
    "discountApplied": "{{percent}}% angewendet",
    "discountForMonths": "Speichere {{percent}}% für den ersten {{months}} Monat",
    "discountForMonths_plural": "Speichere {{percent}}% für die ersten {{months}} Monate",
    "removeDiscount": "Rabatt entfernen",
    "planSummary": "planen",
    "changePlan": "Plan ändern",
    "planDescription": "Sie können Ihren Plan jederzeit ändern oder stornieren.",
    "total": "Gesamt",
    "next": "Nächste",
    "back": "Zurück",
    "fullListOfFeatures": "+ Liste der Funktionen",
    "closeFullListOfFeatures": "− Komplette Liste der Funktionen schließen",
    "frequentlyAskedQuestions": "Häufig gestellte Fragen",
    "seeMorePricing": "Mehr über",
    "pricingComparison": "preisvergleich",
    "easyStartFree": "Einfacher Start, kostenlos mit essentiellen Features.",
    "everythingSimpler": "Mit fortgeschrittener Unterstützung ist alles einfacher.",
    "driveMoreSales": "Führen Sie mehr Verkäufe mit mehr Features.",
    "saveMoreTime": "Sparen Sie mehr Zeit mit Multi-Source-Unterstützung",
    "freeForever": "Frei für immer",
    "billedMonthly": "Monatlich abgerechnet",
    "billedYearly": "Jährlich abgerechnet",
    "perMonth": "monat",
    "discountCode": "Rabattcode",
    "today": "Heute",
    "currency": "USD",
    "chooseFree": "Kostenlos wählen",
    "chooseBasic": "Basic wählen",
    "chooseAdvanced": "Erweiterte auswählen",
    "chooseUnlimited": "Unbegrenzt auswählen",
    "currentPlan": "Aktueller Tarif",
    "daysFreeTrial": "{{days}} Tage kostenlose Testversion",
    "features": {
      "limit20Reviews": "Begrenze 20 Bewertungen für jedes 50 Produkt",
      "productReviewsWidget": "Produkt-Bewertungs-Widget",
      "importReviewsTools": "Bewertungswerkzeuge importieren",
      "importedSourceAliexpress": "Importierte Quelle: Aliexpress",
      "liveChat": "Live-Chat",
      "allInFreePlan": "Alles im kostenlosen Paket",
      "limit200Reviews": "Begrenze 200 Bewertungen für jedes 400 Produkt",
      "featuredReviews": "Empfohlene Bewertungen",
      "questionsAnswers": "Fragen & Antworten",
      "emailRequestReviews": "E-Mail-Rezensionen",
      "importedSourcesAmazonCsv": "Importierte Quellen: +Amazon, CSV",
      "allInBasicPlan": "Alles im Basis-Paket",
      "limit500Reviews": "Begrenze 500 Bewertungen für jedes 1000 Produkt",
      "importSourcesEtsyDHgateWalmart": "Importquellen: + Etsy, DHgate, Walmart.com",
      "fullyCustomizedLayout": "Voll angepasste Layoutoptionen",
      "allInAdvancedPlan": "Alles im Erweiterten Paket",
      "unlimitedReviews": "Unbegrenzte Bewertungen",
      "importMultipleSources": "Bewertungen aus mehreren Quellen für ein Produkt importieren",
      "videoReview": "Videoprüfung",
      "productReviewsFeed": "Feed für Produktbewertungen (XML)",
      "exportBulkReviews": "Massenbewertungen exportieren (CSV)",
      "allGrowthFeatures": "Alle Wachstumsmerkmale"
    },
    "faq": {
      "freePlanQuestion": "Was ist im kostenlosen Plan enthalten?",
      "freePlanAnswer": "Unser kostenloser Plan beinhaltet wesentliche Funktionen wie die Anzeige von Rezensionen, das Hinzufügen von Rezensionen und grundlegende Anpassungsoptionen – ideal für kleinere Geschäfte, die mit Rezensionen beginnen.",
      "switchPlansQuestion": "Kann ich jederzeit den Tarif wechseln?",
      "switchPlansAnswer": "Ja! Sie können Ihren Plan jederzeit aktualisieren oder herabstufen. Änderungen werden sofort wirksam, und Sie werden nur für die Zeit belastet, die Sie für jeden Tarif verwenden.",
      "trialPeriodQuestion": "Gibt es eine Testphase für Prämienpläne?",
      "trialPeriodAnswer": "Ja, wir bieten Ihnen eine Testphase an, um unsere Premium-Funktionen zu erkunden. Sie können die Funktionen testen und sehen, wie sie sich auf Ihren Shop auswirken, bevor Sie diese freigeben.",
      "billingQuestion": "Wie funktioniert die Abrechnung?",
      "billingAnswer": "Die Abrechnung erfolgt monatlich oder jährlich, je nach Präferenz. Die jährliche Abrechnung bietet einen Rabatt im Vergleich zur monatlichen Abrechnung.",
      "cancelQuestion": "Kann ich mein Abonnement kündigen?",
      "cancelAnswer": "Absolut! Sie können jederzeit direkt in Ihren Kontoeinstellungen abbrechen. Einmal abgebrochen, hast du bis zum Ende deines Abrechnungszyklus Zugriff auf die Funktionen deines Paketes.",
      "additionalFeesQuestion": "Gibt es zusätzliche Gebühren?",
      "additionalFeesAnswer": "Nein! Alle Gebühren sind in den Abonnementkosten enthalten. Es gibt keine versteckten Gebühren oder zusätzliche Transaktionsgebühren.",
      "helpDecidingQuestion": "Was ist, wenn ich Hilfe brauche, um zu entscheiden, welcher Plan für mich am besten ist?",
      "helpDecidingAnswer": "Wenn Sie sich nicht sicher sind, hilft Ihnen unser Team! Kontaktieren Sie uns einfach per Chat oder E-Mail, und wir führen Sie zu der besten Option für die Bedürfnisse Ihres Shops."
    },
    "comparison": {
      "pricing": "Preis",
      "payMonthly": "Monatlich bezahlen",
      "payYearly": "Zahle jährlich (bis zu 25%)*",
      "reviewImporter": "Importer überprüfen",
      "reviewsPerProduct": "Bewertungen pro Produkt",
      "totalProducts": "Artikel insgesamt",
      "importedSources": "Importierte Quellen",
      "importMultipleSources": "Mehrere Quellen importieren",
      "syncNewReviews": "Neue Bewertungen synchronisieren",
      "displayWidget": "Widget anzeigen",
      "productReviewsWidget": "Produkt-Bewertungs-Widget",
      "featuredReviews": "Empfohlene Bewertungen",
      "boostSalesPopup": "Boost Sales Popup",
      "questionsAnswers": "Fragen & Antworten",
      "googleRichSnippet": "Google Rich-Schnipsel",
      "customizationWidget": "Anpassungs-Widget",
      "customizeDesign": "Design anpassen",
      "masonryLayout": "Mauerwerk Layout",
      "carouselLayout": "Karussell-Layout",
      "lazyLoadWidget": "Langes Lade-Widget",
      "removeLogoBranding": "Logo-Branding entfernen",
      "photoReview": "Fotobewertung",
      "translateWidget": "Widget übersetzen",
      "requestReviews": "Rezensionen anfordern",
      "emailRequestReviews": "E-Mail-Rezensionen",
      "importExport": "Import / Export",
      "importExportReviewsCsv": "CSV Importieren/Exportieren",
      "importExportQaCsv": "Q&A CSV importieren/exportieren",
      "productReviewsFeedXml": "Feed für Produktbewertungen (XML)",
      "exportBulkReviewsCsv": "Massenbewertungen exportieren (CSV)",
      "support": "Unterstützung",
      "liveChat": "Live-Chat"
    },
    "success": "Abonnement erfolgreich erstellt",
    "error": "Fehler",
    "switchedToFree": "Erfolgreich zum kostenlosen Paket gewechselt"
  },
  "customizeEmail": {
    "title": "E-Mail anpassen",
    "sendTestEmail": "Test-E-Mail senden",
    "general": "Allgemein",
    "subject": "Betreff",
    "colors": "Farben",
    "background": "Hintergrund",
    "customizeSections": "Sektionen anpassen",
    "customize": "Anpassen",
    "backToSections": "Zurück zu den Sektionen",
    "showHeader": "Header anzeigen",
    "headerBackground": "Hintergrund der Kopfzeile",
    "logo": "Logo",
    "currentLogo": "Aktuelles Logo",
    "changeLogo": "Logo ändern",
    "uploadLogo": "Logo hochladen",
    "logoSize": "Logogröße",
    "width": "Width",
    "height": "Höhe",
    "align": "Align",
    "lineColor": "Linienfarbe",
    "removeSection": "Abschnitt entfernen",
    "buttonText": "Schaltflächentext",
    "textColor": "Textfarbe",
    "showFooter": "Footer anzeigen",
    "footerBackground": "Hintergrund Fußzeile",
    "contentFooter": "Inhaltsfußzeile",
    "enterFooterContent": "Footer-Inhalt hier eingeben...",
    "unsubscribeLinkText": "Link-Text abbestellen",
    "text": "Text",
    "starColor": "Sternfarbe",
    "orderItems": "Bestellartikel",
    "orderItemsDescription": "In diesem Bereich werden die Produkte in Ihrer Bestellung angezeigt.",
    "content": "Inhalt",
    "enterContent": "Geben Sie hier Ihren Inhalt ein...",
    "fontWeight": "Schriftgewicht",
    "normal": "Normal",
    "bold": "Bold",
    "image": "Bild",
    "sectionImage": "Abschnittsbild",
    "changeImage": "Bild ändern",
    "uploadImage": "Bild hochladen",
    "imageSize": "Bildgröße",
    "acceptImageTypes": ".jpg, .png, .webp und maximal 2MB akzeptieren",
    "save": "Speichern",
    "discard": "Verwerfen",
    "templateSaved": "Vorlage erfolgreich gespeichert",
    "errorSavingTemplate": "Fehler beim Speichern der Vorlage: {{error}}",
    "sendTestEmailModal": "Test-E-Mail senden",
    "enterEmailAddress": "Geben Sie eine E-Mail-Adresse ein, um eine Test-E-Mail mit Ihrer aktuellen Vorlage zu senden:",
    "emailAddress": "E-Mail-Adresse",
    "sending": "Senden...",
    "send": "Senden",
    "cancel": "Abbrechen",
    "testEmailSentSuccess": "Test-E-Mail erfolgreich gesendet an",
    "pleaseEnterValidEmail": "Bitte geben Sie eine gültige E-Mail-Adresse ein.",
    "uploadingImage": "Bild wird hochgeladen...",
    "back": "Zurück",
    "left": "Links",
    "center": "Zentriert",
    "right": "Rechts",
    "show": "Zeigen",
    "hide": "Verstecken",
    "availableSections": {
      "image": "Bild",
      "text": "Text",
      "orderItems": "Bestellartikel",
      "rateList": "Bewertungsliste",
      "button": "Button",
      "line": "Linie"
    },
    "sections": {
      "header": "Kopfzeile",
      "footer": "Fußzeile",
      "line": "Linie",
      "button": "Button",
      "rating": "Bewertung",
      "text": "Text",
      "image": "Bild",
      "customerName": "Kundenname",
      "thankYou": "Vielen Dank",
      "message": "Nachricht"
    },
    "ratingTexts": {
      "terrible": "Schrecklich",
      "poor": "Arm",
      "average": "Durchschnitt",
      "veryGood": "Sehr gut",
      "excellent": "Ausgezeichnet"
    }
  },
  "emailAutomation": {
    "title": "Überprüfung der E-Mail-Anfrage",
    "backToEmail": "E-Mail",
    "customizeEmail": "E-Mail anpassen",
    "sendAutomatically": "E-Mails zur Überprüfung automatisch senden",
    "webhooksConfiguration": "Webhooks Konfiguration",
    "webhooksDescription": "Dies wird Webhooks für ORDERS_CREATE und ORDERS_UPDATED Events in Ihrem Shopify Shop erstellen.",
    "sendAfter": "Senden nach",
    "oneHour": "1 Stunde",
    "sixHours": "6 Stunden",
    "tenHours": "10 Stunden",
    "twentyFourHours": "24 Stunden",
    "custom": "Eigene",
    "timeDelay": "Zeitverzögerung",
    "timeUnit": "Zeiteinheit",
    "days": "tage",
    "hours": "std",
    "whenOrderStatus": "Bei Bestellstatus",
    "purchased": "Gekauft",
    "fulfilled": "Erfüllt",
    "delivered": "Ausgestellt",
    "afterReviewSubmitted": "Nach Prüfung eingereicht",
    "redirectToCustomizeUrl": "Weiterleitung zur URL anpassen",
    "customizeUrl": "URL anpassen",
    "thankYouPage": "Vielen Dank Seite",
    "thankYouPageDescription": "Dankeschön Seite mit einem Rabattcode einrichten.",
    "thankYouPageLink": "danke für die Seite",
    "updatingSettings": "E-Mail-Automatisierungseinstellungen werden aktualisiert...",
    "settingsSaved": "Einstellungen erfolgreich gespeichert",
    "settingsError": "Fehler beim Speichern der Einstellungen",
    "webhooksCreated": "Webhooks erfolgreich erstellt",
    "webhooksRemoved": "Webhooks erfolgreich entfernt",
    "webhooksError": "Fehler beim Verwalten der Webhooks"
  },
  "emailNotifications": {
    "title": "E-Mail-Benachrichtigung",
    "backToEmail": "E-Mail",
    "type": "Typ",
    "name": "Name",
    "pendingDomainVerification": "Ausstehende Domänenüberprüfung",
    "pendingDomainDescription": "Sie haben {{count}} Domain(s) warten auf Überprüfung: {{domains}}.",
    "pendingDomainInstructions": "Bitte vervollständigen Sie den Verifizierungsprozess, indem Sie die erforderlichen DNS-Datensätze hinzufügen. Gehen Sie zum Abschnitt Domain Verifizierung unten und klicken Sie auf Domain verifizieren, um die erforderlichen DNS-Einträge zu sehen.",
    "emailVerificationRequired": "E-Mail-Verifizierung erforderlich",
    "emailVerificationInProgress": "E-Mail-Verifizierung wird durchgeführt",
    "emailVerificationDescription": "Diese E-Mail muss mit AWS SES überprüft werden, bevor Sie E-Mails versenden können. Klicken Sie auf \"E-Mail verifizieren\", um den Verifizierungsprozess zu starten.",
    "emailVerificationSent": "Eine Bestätigungs-E-Mail wurde an {{email}}gesendet. Bitte überprüfen Sie Ihren Posteingang und klicken Sie auf den Bestätigungslink.",
    "saveToVerify": "Klicken Sie oben auf der Seite speichern, um diese E-Mail zu speichern und zu bestätigen",
    "senderEmail": "Absender-E-Mail",
    "fromEmail": "Von E-Mail",
    "fromDomain": "Von Domäne",
    "fromDomainHelpText": "Der Domain-Teil Ihrer Absender-E-Mail (z.B. 'beispiel.com')",
    "fromName": "Absendername",
    "verifyEmail": "E-Mail bestätigen",
    "checkAgain": "Erneut prüfen",
    "verifyingEmail": "E-Mail wird überprüft...",
    "checkingVerification": "Überprüfe Überprüfung...",
    "domainVerification": "Domain Verifizierung",
    "domainVerificationDescription": "Überprüfen Sie Ihre Domain mit AWS SES um E-Mails von Ihrer Domain zu senden.",
    "pendingDomains": "Ausstehende Domains",
    "domainsWaitingForVerification": "Domänen, die auf Überprüfung warten",
    "viewDnsRecords": "DNS-Einträge anzeigen",
    "checkStatus": "Status prüfen",
    "domainToVerify": "Domain zu verifizieren",
    "domainToVerifyHelpText": "Geben Sie Ihre Domain ohne 'www', z.B. 'example.com' ein",
    "domainVerified": "Domain verifiziert",
    "domainVerifiedDescription": "Domain {{domain}} wurde erfolgreich verifiziert.",
    "dkim": "DKIM",
    "mailFrom": "MAIL AUS",
    "verified": "Verifiziert",
    "notVerified": "Nicht verifiziert",
    "pending": "Ausstehend",
    "refreshVerificationStatus": "Überprüfungsstatus aktualisieren",
    "checkingVerificationStatus": "Überprüfe den Bestätigungsstatus...",
    "domainPartiallyVerified": "Domain teilweise überprüft",
    "domainPartiallyVerifiedDescription": "Domain ist verifiziert, aber DKIM Verifizierung steht noch aus. Bitte vervollständigen Sie das DNS-Setup.",
    "checkDomainStatus": "Domänenstatus überprüfen",
    "checkingDomainStatus": "Domain-Status wird überprüft...",
    "verifyDomain": "Domain überprüfen",
    "refreshVerification": "Verifizierung aktualisieren",
    "startingVerification": "Beginne Überprüfung...",
    "saveDomainFirst": "Klicken Sie oben auf der Seite auf Speichern, um diese Domain zu speichern, bevor sie bestätigt wird",
    "domainVerificationInstructions": "Domänenüberprüfungsanleitung",
    "addDnsRecordsDescription": "Fügen Sie folgende DNS-Einträge zu Ihrer Domain hinzu, um sie mit AWS SES zu überprüfen:",
    "dkimRecords": "DKIM-Datensätze (CNAME)",
    "customMailFromDomain": "Eigene MAIL-DROM-Domain",
    "customMailFromDescription": "Die Einrichtung einer eigenen MAIL FROM Domäne verbessert die Zustellbarkeit von E-Mails und verhindert SPF Ausrichtungsprobleme.",
    "value": "Wert",
    "copyToClipboard": "In Zwischenablage kopieren",
    "notification": "Benachrichtigung",
    "notificationDescription": "Die E-Mail, die Ihr Shop verwendet, um E-Mails an Ihre Kunden zu senden.",
    "newReviewNotification": "Neue Bewertungsbenachrichtigung",
    "customer": "Kunde",
    "admin": "Admin",
    "disable": "Deaktivieren",
    "enable": "Aktivieren",
    "savedSuccessfully": "Erfolgreich gespeichert",
    "invalidEmail": "Ungültige E-Mail. Bitte korrigieren Sie vor dem Speichern.",
    "invalidDomain": "Ungültige Domain. Bitte korrigieren Sie vor dem Speichern.",
    "emailInvalid": "Email invalid",
    "domainInvalid": "Ungültige Domain. Beispiel: example.com",
    "verificationEmailSent": "Bestätigungs-E-Mail an {{email}}gesendet. Bitte überprüfen Sie Ihren Posteingang.",
    "emailVerified": "E-Mail verifiziert",
    "emailVerifiedDescription": "Ihre E-Mail {{email}} ist verifiziert und kann verwendet werden.",
    "verificationEmailSentTitle": "Verifizierungs-E-Mail gesendet",
    "verificationEmailSentDescription": "Eine Bestätigungs-E-Mail wurde an {{email}}gesendet. Bitte überprüfen Sie Ihren Posteingang und folgen Sie den Anweisungen, um ihn zu überprüfen.",
    "verificationError": "Verifizierungsfehler",
    "verificationErrorMessage": "Beim Überprüfen dieser E-Mail ist ein Fehler aufgetreten. Bitte versuchen Sie es erneut.",
    "domainVerifiedSuccess": "Domain verifiziert",
    "domainSaved": "Domain gespeichert",
    "savingDomain": "Domain speichern...",
    "errorSavingDomain": "Fehler beim Speichern der Domain",
    "pleaseEnterDomain": "Bitte geben Sie eine Domain zur Verifizierung ein",
    "copiedSuccessfully": "Kopiert erfolgreich",
    "copyFailed": "Kopieren fehlgeschlagen",
    "updatingEmailSettings": "Aktualisiere E-Mail-Benachrichtigungseinstellungen...",
    "emailSettingsSaved": "E-Mail-Benachrichtigungseinstellungen erfolgreich gespeichert",
    "emailSettingsError": "Fehler beim Speichern der E-Mail-Benachrichtigungseinstellungen"
  },
  "importReviews": {
    "title": "Bewertungen nach URL importieren",
    "backToProducts": "Produkte",
    "importSettings": "Import-Einstellungen",
    "selectProduct": "Produkt auswählen",
    "changeProduct": "Produkt ändern",
    "noProductSelected": "Kein Produkt ausgewählt",
    "noProductSelectedDescription": "Bitte wählen Sie ein Produkt aus Ihrem Shop, um Bewertungen zu importieren",
    "showReviews": "Bewertungen anzeigen",
    "hideReviews": "Bewertungen ausblenden",
    "dropshippingUrlList": "Dropshipping URL Liste",
    "addUrl": "URL hinzufügen",
    "pleaseSelectProductFirst": "Bitte wählen Sie ein Produkt aus der linken Seitenleiste aus, bevor Sie URLs hinzufügen.",
    "learnMore": "Mehr erfahren",
    "url": "URL",
    "urlPlaceholder": "https://www.aliexpress.com/item/10050031234567890.html",
    "urlSupportText": "Unterstützen Sie Aliexpress, Amazon, Etsy, DHgate oder Walmart Produkt URL.",
    "invalidUrlError": "Bitte geben Sie eine gültige Produkt-URL von unterstützten Plattformen ein",
    "pleaseEnterUrl": "Bitte eine URL eingeben",
    "pleaseSelectProductFirstError": "Bitte wählen Sie zuerst ein Produkt",
    "importReviews": "Bewertungen importieren",
    "loadMoreReviews": "Weitere Bewertungen laden",
    "syncNewReviews": "Neue Bewertungen synchronisieren",
    "reviewsLoaded": "Bewertungen geladen.",
    "urlAdded": "URL hinzugefügt.",
    "urlDeleted": "URL gelöscht.",
    "failedToLoadReviews": "Fehler beim Laden der Bewertungen.",
    "noReviewsError": "Dieses Produkt hat keine Bewertungen.",
    "failedToGetReviews": "Fehler beim Abrufen der Bewertungsinformationen",
    "addProduct": "Produkt hinzufügen",
    "searchPlaceholder": "Suchen",
    "product": "produkt",
    "products": "artikel",
    "reviewsAvailable": "verfügbare Bewertungen",
    "reviewsLoadedCount": "rezensionen",
    "contactUs": "Kontaktiere uns",
    "dropshipProductNoReviews": "Das Dropship-Produkt hat keine Bewertungen",
    "successfully": "Erfolgreich:",
    "failedToImport": "Import fehlgeschlagen:",
    "duplicatesSkipped": "Duplikate übersprungen:",
    "deleteUrlTitle": "URL löschen",
    "deleteUrlMessage": "Sind Sie sicher, dass Sie diese URL löschen möchten? Diese Aktion kann nicht rückgängig gemacht werden.",
    "deleteUrl": "URL löschen",
    "amazonLimit100Tooltip": "100 Bewertungen pro Amazon Artikel begrenzen",
    "almostThere": "Fast fertig!",
    "pleaseStayOnThisPageUntilWeFinish": "Bitte bleiben Sie auf dieser Seite bis wir fertig sind.",
    "importSuccessful": "Import erfolgreich",
    "reviewsImportedSuccessfully": "Bewertungen erfolgreich importiert.",
    "youHaveReachedYourLimit": "Sie haben Ihr Limit erreicht.",
    "youHaveReachedTheImportedReviewLimit": "Sie haben mit Ihrem Ryviu-Plan das importierte Überprüfungslimit für dieses Produkt erreicht.",
    "installExtension": "Installieren Sie die Ryviu Chrome-Erweiterung.",
    "installExtensionDescription": "Installieren Sie die Free Ryviu Chrome Erweiterung um Bewertungen von URLs zu importieren.",
    "productImportLimit": "Sie haben das Limit für die Anzahl der Produkte erreicht, die Bewertungen auf Ihrem Ryviu-Plan importieren können.",
    "notSupportSourceWithYourPlan": "Diese Quelle wird mit Ihrem Ryviu-Plan nicht unterstützt."
  },
  "productsPage": {
    "title": "Produkte",
    "importReviews": "Bewertungen importieren",
    "moreActions": "Weitere Aktionen",
    "exportAllReviews": "Alle Bewertungen exportieren",
    "productReviewsFeed": "Feed Produktbewertungen",
    "exportSuccess": "Export erfolgreich.",
    "exportedBanner": "Bewertungen wurden exportiert. Bitte überprüfen Sie Ihre E-Mail, um die csv-Datei herunterzuladen.",
    "exportedBannerText": "Bewertungen wurden exportiert. Bitte überprüfen Sie Ihre E-Mail, um die csv-Datei herunterzuladen.",
    "noProductsSelected": "Keine Produkte ausgewählt.",
    "showReviews": "Bewertungen anzeigen",
    "hideReviews": "Bewertungen ausblenden",
    "hasReviews": "Hat Bewertungen",
    "hasQuestions": "Hat Fragen",
    "image": "Bild",
    "titleCol": "Titel",
    "reviews": "Bewertungen",
    "qa": "Q&A",
    "reviewsStatus": "Bewertungsstatus",
    "viewProduct": "Artikel in Ihrem Shop anzeigen",
    "exportReviewsCsv": "CSV Bewertungen exportieren",
    "googleFeed": "Google Feed",
    "duplicate": "Duplicate",
    "duplicateReviews": "Bewertungen duplizieren",
    "deleteAllReviews": "Alle Bewertungen löschen",
    "cannotBeUndone": "Dies kann nicht rückgängig gemacht werden.",
    "productGoogleShopInfo": "Produkt Google Shop Info",
    "productUrl": "Produkt-URL",
    "gtins": "GINs",
    "skus": "SKUs",
    "asins": "ASINs",
    "productTitle": "Produkttitel",
    "mpns": "MPN",
    "brands": "Marken",
    "downloadXml": "XML herunterladen",
    "reviewsImportedSuccess": "Bewertungen erfolgreich importiert.",
    "reviewsImportedSuccessToast": "Bewertungen erfolgreich importiert.",
    "productNoReviews": "Dieses Produkt hat keine Bewertungen.",
    "errorExportGoogleFeed": "Fehler beim Exportieren von Google Feed",
    "googleFeedExportedSuccess": "Google Feed XML erfolgreich exportiert!",
    "googleFeedExportedToast": "Google Feed XML erfolgreich exportiert!",
    "noReviewsDataToExport": "Keine zu exportierenden Bewertungsdaten",
    "noReviewsDataToExportToast": "Keine zu exportierenden Bewertungsdaten.",
    "tabAll": "Alle",
    "tabShowReviews": "Bewertungen anzeigen",
    "tabHideReviews": "Bewertungen ausblenden",
    "tabHasReviews": "Hat Bewertungen",
    "tabHasQuestions": "Hat Fragen",
    "searchPlaceholder": "Suche in allen",
    "searchingInAll": "Suche in allen",
    "exportSuccessToast": "Export erfolgreich.",
    "productSavedToast": "Produkt gespeichert.",
    "reviewsDeletedToast": "Bewertungen gelöscht.",
    "productsSavedToast": "Produkte gespeichert.",
    "noProductsSelectedToast": "Keine Produkte ausgewählt.",
    "cantExportToast": "Bewertungen können nicht exportiert werden.",
    "bulkDeleteTitle": "Alle Bewertungen von {{count}} Produkten löschen",
    "aToZ": "A Z",
    "zToA": "Z-A",
    "show": "Zeigen",
    "hide": "Verstecken",
    "viewProductTooltip": "Artikel in Ihrem Shop anzeigen",
    "createdAt": "Erstellt am",
    "product": "produkt",
    "products": "artikel",
    "exportCsv": "CSV exportieren",
    "exportGoogleFeed": "Google Feed exportieren",
    "reviewsCopiedSuccess": "Bewertungen erfolgreich kopiert.",
    "failedToCopyReviews": "Fehler beim Kopieren der Bewertungen: ",
    "copyReviewsError": "Fehler beim Kopieren der Bewertungen.",
    "copyReviews": "Bewertungen kopieren",
    "chromeRequired": "Chrome-Browser erforderlich",
    "chromeRequiredDescription": "Die Importbewertungsfunktion erfordert das einwandfreie Funktionieren des Chrome-Browsers. Bitte wechseln Sie zu Chrome, um diese Funktion zu nutzen.",
    "chromeRequiredTooltip": "Unterstützt nur Chrome Browser"
  },
  "copyReviewsModal": {
    "from": "Von",
    "to": "An",
    "searchProductsPlaceholder": "Produkte suchen...",
    "searchingProducts": "Produkte suchen...",
    "noProductsFound": "Keine Produkte gefunden.",
    "reviews": "rezensionen"
  },
  "importSettings": {
    "generalDescription": "Allgemeine Einstellungen für den Import von Produktbewertungen verwalten.",
    "removeDuplicateReviews": "Duplikate Bewertungen entfernen",
    "importImageReviewsOnly": "Nur Bildbewertungen importieren",
    "reviewQuantityPerImport": "Menge pro Import überprüfen",
    "optionForAliexpress": "Option für Aliexpress",
    "optionForAliexpressDesc": "Passen Sie an, wie Bewertungen von Aliexpress importiert werden.",
    "translateReviews": "Rezensionen übersetzen",
    "optionForAmazon": "Option für Amazon",
    "optionForAmazonDesc": "Aktivieren oder deaktivieren Sie den Import von Produktbewertungen von ASIN aus Amazon.",
    "importByASIN": "Von ASIN importieren",
    "syncNewReviews": "Neue Bewertungen synchronisieren",
    "syncNewReviewsDesc": "Legen Sie die Zeitspanne für die Aktualisierung neuer Bewertungen fest.",
    "updateReviewsInDateRange": "Bewertungen im Datumsbereich aktualisieren",
    "last7Days": "Letzte 7 Tage",
    "last30Days": "Letzte 30 Tage",
    "last90Days": "Letzte 90 Tage",
    "last180Days": "Letzte 180 Tage",
    "last365Days": "Letzte 365 Tage",
    "filterByCountry": "Nach Land filtern"
  }
}