{
  "common": {
    "save": "Enregistrer",
    "activity": "Activité",
    "cancel": "Abandonner",
    "delete": "Supprimez",
    "edit": "Editer",
    "add": "Ajouter",
    "remove": "Retirer",
    "confirm": "Valider",
    "back": "Précédent",
    "next": "Suivant",
    "previous": "Précédent",
    "loading": "Chargement en cours...",
    "error": "Erreur",
    "success": "Succès",
    "warning": "Avertissement",
    "info": "Information",
    "yes": "Oui",
    "no": "Non",
    "ok": "Ok",
    "close": "Fermer",
    "search": "Chercher",
    "filter": "Filtre",
    "sort": "Trier",
    "refresh": "Rafraîchir",
    "export": "Exportation",
    "exportCSV": "Exporter CSV",
    "import": "Importation",
    "upload": "Charger",
    "download": "Télécharger",
    "chatNow": "Discuter maintenant",
    "copy": "Copie",
    "paste": "Coller",
    "select": "Sélectionner",
    "all": "Tous",
    "none": "Aucun",
    "actions": "Actions",
    "status": "Statut",
    "date": "Date",
    "createdAt": "Créé le",
    "time": "Date et heure",
    "name": "Nom",
    "description": "Libellé",
    "type": "Type de texte",
    "category": "Catégorie",
    "tags": "Tags",
    "language": "Langue",
    "english": "Anglais",
    "french": "Français",
    "german": "Allemand",
    "spanish": "Espagnol",
    "japanese": "Japonais",
    "portuguese": "Portugais",
    "italian": "Italien",
    "chinese": "Chinois",
    "vietnamese": "Vietnamese",
    "show": "Afficher",
    "hide": "Cacher",
    "uploadCSVFile": "Charger un fichier CSV",
    "downloadSampleCSV": "Télécharger le fichier CSV",
    "acceptsCSV": "Accepte les fichiers .csv",
    "countryUnitedStates": "États-Unis",
    "countryVietnam": "Vietnam",
    "countryChina": "La Chine",
    "enable": "Activer",
    "disable": "Désactiver",
    "paid": "Payé",
    "total": "Total",
    "sent": "Envoyé",
    "scheduled": "Planifié",
    "opened": "Ouvert",
    "rated": "Évalué",
    "failed": "Echoué",
    "notSend": "Ne pas envoyer",
    "static": "Statique",
    "emails": "E-mails",
    "questions": "Questions",
    "reviews": "Revues",
    "review": "Évaluer",
    "learnMoreAbout": "En savoir plus sur",
    "widgetsSection": "Section des widgets",
    "productsSection": "Section produits",
    "products": "Produits",
    "product": "Produit",
    "reviewsSection": "Section des avis",
    "questionsSection": "Section des questions",
    "emailsSection": "Section E-mails",
    "updateAndSendEmail": "Mettre à jour et envoyer un e-mail",
    "helpful": "Aide :",
    "images": "Images",
    "upgradeNow": "Mettre à niveau maintenant",
    "getHelp": "Obtenir de l'aide",
    "installNow": "Installer maintenant"
  },
  "settings": {
    "title": "Réglages",
    "annuallyAt": "Annuellement à",
    "monthlyAt": "Mensuel à",
    "profile": "Profil",
    "membership": "Adhésion",
    "firstName": "Prénom",
    "lastName": "Nom de famille",
    "email": "Courriel",
    "username": "Nom d'utilisateur",
    "adminLanguage": "Langue de l'administrateur",
    "timezone": "Fuseaux horaires",
    "languageAndTimezone": "Langue et fuseau horaire",
    "yourPlan": "Votre abonnement",
    "billingCycle": "Cycle de facturation",
    "renewalDate": "Date de renouvellement",
    "unsubscribe": "Se désabonner",
    "editMembership": "Modifier l'adhésion",
    "uploadFiles": "Charger des fichiers",
    "unsubscribeFromPlan": "Se désabonner de votre forfait ?",
    "unsubscribing": "Désabonnement...",
    "yesUnsubscribe": "Oui, vous désabonner",
    "unsubscribeWarning": "Êtes-vous sûr de vouloir vous désabonner ? Vous perdrez l'accès aux fonctionnalités premium à la fin de votre cycle de facturation.",
    "unsubscribeConfirm": "Êtes-vous sûr de vouloir vous désabonner ?",
    "unsubscribeSuccess": "Vous avez été désabonné avec succès.",
    "unsubscribeError": "Une erreur s'est produite lors de la désinscription.",
    "unsubscribeConfirmText": "Êtes-vous sûr de vouloir vous désabonner ?",
    "unsubscribeSuccessText": "Vous avez été désabonné avec succès.",
    "unsubscribeErrorText": "Une erreur s'est produite lors de la désinscription.",
    "CLICK_TO_ACT": "Cliquez pour agir",
    "FEATURED_POPUP": "Pop-up en vedette",
    "REVIEWS_PAGE_URL": "URL de la page de commentaires",
    "FEATURED_PAGE_URL": "URL de la page en vedette",
    "LAYOUT": "Mise en page",
    "WIDGET_STYLE": "Style du widget",
    "BADGE_ORIENTATION": "Orientation du badge",
    "SHOW_HEADER": "Afficher l'en-tête",
    "STORE_NAME": "Nom du magasin",
    "IMAGE_HEIGHT": "Hauteur de l'image",
    "IMAGE_BADGE": "Insigne image",
    "LABEL_BACKGROUND": "Arrière-plan",
    "TEXT_COLOR": "Couleur du texte"
  },
  "reviews": {
    "allReviews": "Tous les commentaires",
    "pendingReviews": "Avis en attente",
    "approvedReviews": "Avis approuvés",
    "rejectedReviews": "Avis rejetés",
    "reviewDetails": "Détails de la revue",
    "reviewer": "Evaluateur",
    "rating": "Évaluation",
    "comment": "Commenter",
    "approve": "Approuver",
    "reject": "Refuser",
    "view": "Voir",
    "noReviews": "Aucun commentaire trouvé",
    "exportReviews": "Exporter les commentaires",
    "bulkActions": {
      "setFeatured": "Mettre en vedette",
      "unsetFeatured": "Ne plus mettre en vedette",
      "delete": "Supprimez"
    },
    "selectAll": "Tout sélectionner",
    "deselectAll": "Désélectionner tout",
    "filterByStatus": "Filtrer par statut",
    "filterByRating": "Filtrer par note",
    "filterByDate": "Filtrer par date",
    "searchReviews": "Rechercher des commentaires...",
    "reviewCount": "Revue {{count}}",
    "reviewCount_plural": "Avis {{count}}",
    "static": "Statique",
    "average": "Moyenne",
    "totalReviews": "Total des avis",
    "unpublish": "Dépublier",
    "reviews": "Revues",
    "author": "Auteur",
    "content": "Contenus",
    "comments": "Commentaires",
    "featured": "En vedette",
    "publish": "Publier",
    "unpublished": "Non publié",
    "published": "Publié",
    "removeFeatured": "Supprimer les éléments en vedette",
    "setAsFeatured": "Définir comme en vedette",
    "editReview": "Modifier la revue",
    "deleteReview": "Supprimer la revue",
    "viewProduct": "Voir le produit sur votre boutique",
    "editReviews": "Modifier les avis",
    "title": "Titre de la page",
    "images": "Images",
    "acceptsImages": "Accepte .gif, .jpg et .png",
    "deleteReviewTitle": "Supprimer le commentaire ?",
    "cannotBeUndone": "Cela ne peut pas être annulé.",
    "deleteAllReviewsTitle": "Supprimer tous les avis ?",
    "deleting": "Suppression en cours...",
    "deletingReview": "Suppression de la révision...",
    "saving": "Sauvegarde en cours...",
    "reviewSaved": "Enregistré",
    "reviewDeleted": "Revue supprimée.",
    "allReviewsDeleted": "Toutes les évaluations ont été supprimées avec succès.",
    "reviewSavedStatus": "Révision enregistrée.",
    "bulkActionSuccess": {
      "show": "Avis affichés avec succès",
      "hide": "Avis masqués avec succès",
      "feature": "Avis définis en vedette",
      "unfeature": "Les avis ne sont plus mis en vedette"
    },
    "bulkActionTitles": {
      "show": "Définir les avis {{count}} à publier?",
      "hide": "Définir les avis {{count}} comme non publiés ?",
      "feature": "Définir les avis {{count}} comme fonctionnels?",
      "unfeature": "Ne plus mettre en vedette pour les avis {{count}}?"
    },
    "bulkActionDescriptions": {
      "show": "Définir ces avis à publier le rendra disponible sur votre page produit.",
      "hide": "Définir ces avis à unpublished les masquera de votre page produit.",
      "feature": "Définir ces avis comme mis en avant les mettra en évidence sur votre page produit.",
      "unfeature": "Ne pas mettre en vedette supprimera la mise en surbrillance de ces commentaires."
    },
    "bulkActionButtons": {
      "show": "Définir comme publication",
      "hide": "Définir comme dépublié",
      "feature": "Définir en vedette",
      "unfeature": "Ne plus mettre en vedette"
    },
    "promotedBulkActions": {
      "publish": "Publier",
      "unpublish": "Dépublier"
    },
    "filters": {
      "rating": "Évaluation",
      "type": "Évaluer",
      "source": "Source",
      "star": "Étoiles",
      "onlyText": "Texte uniquement",
      "photo": "Photo",
      "aliexpress": "AliExpress",
      "amazon": "Amazon",
      "etsy": "Etsy",
      "dhgate": "DHgate",
      "walmart": "Vauban",
      "shopee": "Shopie",
      "csv": "CSV",
      "email": "Courriel"
    },
    "tabs": {
      "all": "Tous",
      "published": "Publié",
      "unpublished": "Non publié",
      "featured": "En vedette",
      "notFeatured": "Non en vedette"
    },
    "sortOptions": {
      "createdAtAsc": "Créé le",
      "createdAtDesc": "Créé le",
      "importedAtAsc": "Importé le",
      "importedAtDesc": "Importé le"
    },
    "searchPlaceholder": "Recherche dans tous les",
    "moreActions": "Plus d'actions",
    "viewOnStore": "Voir sur la boutique",
    "deleteAllReviews": "Supprimer tous les avis",
    "importCSV": "Importer CSV",
    "importReviews": "Importer les avis",
    "reviewsVisible": "Avis visibles",
    "reviewsHidden": "Avis cachés",
    "back": "Précédent",
    "product": "Produit",
    "repliesList": "Liste des réponses",
    "nothingHere": "Rien ici",
    "noReplies": "Il n'y a aucune réponse",
    "leaveComment": "Laisser un commentaire...",
    "send": "Envoyer",
    "replyAdded": "Réponse ajoutée.",
    "replySaved": "Réponse enregistrée.",
    "replyDeleted": "Réponse supprimée.",
    "deletingReply": "Suppression en cours...",
    "savingReply": "Sauvegarde en cours...",
    "shopifyTermsWarning": "Vous n'êtes autorisé qu'à corriger la grammaire ou à clarifier le contenu de la revue. L'évaluation des étoiles ne peut pas être modifiée.",
    "shopifyPartnerAgreement": "Contrat de programme partenaire Shopify",
    "filterLabels": {
      "rating": "Évaluation : {{value}}",
      "type": "Type de revue : {{value}}",
      "source": "Source: {{value}}"
    },
    "deleteAllReviewsOfProducts": "Supprimer tous les avis sur les produits {{count}}",
    "exportCsv": "Exporter CSV",
    "exportGoogleFeed": "Exporter le flux Google",
    "importing": "Importation en cours...",
    "importCompleted": "Importation terminée !",
    "importSuccess": "Révisions {{count}} importées avec succès.",
    "importErrors": "Erreurs {{count}}:",
    "importFailed": "Échec de l'importation.",
    "csvFormatNote": "Veuillez vous assurer que votre fichier CSV respecte le format requis :",
    "productHandleRequired": "product_handle (obligatoire)",
    "ratingRequired": "note (requise, entière)",
    "emailRequired": "email (obligatoire, adresse e-mail valide)",
    "createdAtOptional": "created_at (optionnel)",
    "averageTooltipProduct": "Évaluation moyenne du produit",
    "averageTooltipShop": "Évaluation moyenne de la boutique",
    "totalTooltip": "Nombre total de revues",
    "totalWithPhotoTooltip": "Nombre total de commentaires avec des photos",
    "totalWithVideoTooltip": "Nombre total de commentaires avec des vidéos",
    "totalWithTextTooltip": "Nombre total de revues avec texte",
    "totalWithAnswerTooltip": "Nombre total de revues avec réponses",
    "totalWithLikeTooltip": "Nombre total de commentaires avec des J'aime",
    "totalReviewsTooltip": "Nombre total de revues",
    "unpublishTooltip": "Nombre d'avis non publiés",
    "totalReviewsTooltipProduct": "Nombre total de commentaires pour le produit",
    "unpublishTooltipProduct": "Nombre d'avis non publiés pour le produit",
    "reasonEditReview": "Veuillez fournir une raison pour votre modification.",
    "reasonEditReviewPlaceholder": "Entrez la raison",
    "reasonEditReviewHelpText": "Nous enverrons également un e-mail au réviseur original pour confirmer les modifications que vous avez suggérées.",
    "starRatingsFixed": "Les cotes en étoiles sont fixes et ne peuvent pas être modifiées."
  },
  "products": {
    "title": "Produits",
    "allProducts": "Tous les produits",
    "productDetails": "Détails du produit",
    "productName": "Nom du produit",
    "productId": "ID du produit",
    "sku": "UGS",
    "price": "Prix",
    "brand": "Marque",
    "images": "Images",
    "variants": "Variantes",
    "inventory": "Inventaire",
    "active": "Actif",
    "inactive": "Inactif",
    "draft": "Brouillon",
    "published": "Publié",
    "importProducts": "Importer des produits",
    "exportProducts": "Exporter les produits",
    "noProducts": "Aucun produit trouvé",
    "productCount": "{{count}} product",
    "productCount_plural": "Produits {{count}}",
    "importSettings": "Importer les paramètres",
    "importFromCSV": "Importer depuis un CSV",
    "importFromAliExpress": "Importer depuis AliExpress",
    "importFromAmazon": "Importer depuis Amazon",
    "importFromEtsy": "Importer depuis Etsy",
    "productStatus": "Statut du produit"
  },
  "questions": {
    "title": "Questions",
    "allQuestions": "Toutes les questions",
    "questionDetails": "Détails de la question",
    "question": "Question",
    "answer": "Répondre",
    "asker": "Demandeur",
    "respondent": "Responsable",
    "pending": "En attente",
    "answered": "Répondu",
    "rejected": "Rejeté",
    "approve": "Approuver",
    "reject": "Refuser",
    "view": "Voir",
    "addQuestion": "Ajouter une question",
    "editQuestion": "Modifier la question",
    "deleteQuestion": "Supprimer la question",
    "importQuestions": "Importer des questions",
    "exportQuestions": "Exporter les questions",
    "bulkActions": "Actions en bloc",
    "selectAll": "Tout sélectionner",
    "deselectAll": "Désélectionner tout",
    "filterByStatus": "Filtrer par statut",
    "filterByDate": "Filtrer par date",
    "searchQuestions": "Rechercher des questions...",
    "noQuestions": "Aucune question trouvée",
    "questionCount": "Question {{count}}",
    "questionCount_plural": "{{count}} questions",
    "importFromCSV": "Importer depuis un CSV",
    "questionType": "Type de question",
    "general": "Généraux",
    "productSpecific": "Spécifique au produit",
    "customerService": "Service à la clientèle",
    "technical": "Technique",
    "author": "Auteur",
    "publish": "Publier",
    "unpublish": "Dépublier",
    "published": "Publié",
    "unpublished": "Dépublier",
    "like": "J'aime",
    "dislike": "Dislike",
    "likes": "J'aime",
    "dislikes": "Dislikes",
    "hasAnswer": "A une réponse",
    "comments": "Commentaires",
    "send": "Envoyer",
    "leaveAnswer": "Laisser une réponse...",
    "nothingHere": "Rien ici",
    "noAnswers": "Il n'y a aucune réponse",
    "areYouSureDelete": "Êtes-vous sûr de vouloir supprimer cette réponse ?",
    "sureDeleteAnswer": "Êtes-vous sûr de vouloir supprimer cette réponse ?",
    "yesDelete": "Oui, supprimer",
    "updating": "Mise à jour de la question...",
    "questionSaved": "Question enregistrée.",
    "questionDeleted": "Question supprimée.",
    "questionsDeleted": "Les questions ont été supprimées.",
    "answerSaved": "Réponse enregistrée",
    "answerDeleted": "Réponse supprimée",
    "questionsUpdated": "Questions mises à jour.",
    "failedToUpdate": "Impossible de mettre à jour la question",
    "failedToDelete": "Échec de la suppression de la question",
    "deleteQuestionTitle": "Supprimer la question",
    "deleteQuestionsTitle": "Supprimer les questions {{count}}",
    "cannotBeUndone": "Cela ne peut pas être annulé.",
    "publishQuestionsTitle": "Publier les questions {{count}}",
    "unpublishQuestionsTitle": "Dépublier les questions {{count}}",
    "sureToPublish": "Êtes-vous sûr de vouloir publier ces questions ?",
    "sureToUnpublish": "Êtes-vous sûr de vouloir annuler la publication de ces questions ?",
    "searchPlaceholder": "Rechercher dans les questions et les auteurs",
    "createdAt": "Créé le",
    "authorSort": "Auteur",
    "answersList": "Liste des réponses",
    "editQuestionTitle": "Modifier les questions",
    "questionRequired": "La question est requise",
    "authorRequired": "L'auteur est requis",
    "fileUploadedInfo": "Fichier téléchargé! Vous pouvez maintenant importer des questions.",
    "importing": "Importation en cours...",
    "importSuccess": "Importation réussie!",
    "importFailed": "Importation échouée",
    "fileSizeLimit": "La taille du fichier dépasse la limite de 1 Mo",
    "csvMissingFields": "Il manque des champs obligatoires au format CSV : product_handle, auteur, email, question",
    "csvInvalidRows": "CSV a une ligne {{count}} invalide. Chaque ligne doit contenir tous les champs obligatoires.",
    "csvParseError": "CSV parse error: {{message}}",
    "cannotReadFile": "Impossible de lire le fichier",
    "uploadFailed": "Échec du téléversement : {{message}}",
    "rowsFailedToImport": "{{count}} row(s) failed to import:",
    "row": "Ligne",
    "upgradeBanner": {
      "title": "Mise à niveau pour débloquer les fonctionnalités de Q&A",
      "desc": "La fonction Question and Answer est exclusivement disponible pour les régimes payés. Mettez à niveau votre compte maintenant pour activer les Q&A et engager directement avec vos clients pour construire des conversions de confiance et de conduite.",
      "upgradeNow": "Mettre à niveau maintenant",
      "learnMore": "En savoir plus"
    },
    "titleTooltip": "Nombre de questions sur le magasin",
    "answeredTooltip": "Nombre de réponses sur le magasin",
    "likeTooltip": "Nombre d'\"J'aime\" sur la boutique",
    "dislikeTooltip": "Nombre de personnes qui n'aiment pas dans la boutique",
    "questionsTooltipProduct": "Nombre de questions sur le produit",
    "answeredTooltipProduct": "Nombre de réponses sur le produit",
    "likeTooltipProduct": "Nombre d'\"J'aime\" sur le produit",
    "dislikeTooltipProduct": "Nombre de J'aime mal sur le produit",
    "importCSVNotAvailable": "Import CSV non disponible",
    "importCSVNotAvailableDescription": "Importer CSV ne prend pas en charge l'offre Gratuite. Veuillez passer à une offre payante pour utiliser cette fonctionnalité."
  },
  "widgets": {
    "title": "Widgets",
    "allWidgets": "Tous les Widgets",
    "widgetDetails": "Détails du Widget",
    "widgetName": "Nom du Widget",
    "widgetType": "Type de widget",
    "widgetId": "ID du widget",
    "active": "Actif",
    "inactive": "Inactif",
    "draft": "Brouillon",
    "published": "Publié",
    "importWidgets": "Importer des Widgets",
    "exportWidgets": "Exporter les Widgets",
    "noWidgets": "Aucun widget trouvé",
    "widgetCount": "Widget {{count}}",
    "widgetCount_plural": "Widgets {{count}}",
    "enableAppEmbed": "Activer l'intégration de l'application",
    "moreDetails": "Plus de détails",
    "customize": "Personnaliser",
    "addNow": "Ajouter maintenant",
    "enableNow": "Activer maintenant",
    "heading": "Titres",
    "rateList": "Liste des tarifs",
    "reviewImagesList": "Voir la liste des images",
    "showingText": "Affichage du texte",
    "customizeWidgetTexts": "Personnaliser les textes du Widget",
    "general": "Généraux",
    "layout": "Mise en page",
    "color": "Couleur",
    "typography": "Typographie",
    "sections": "Sections",
    "formatting": "Formatage en cours",
    "author": "Auteur",
    "media": "Médias",
    "stars": "Étoiles",
    "widgetStyle": "Style du widget",
    "language": "Langue",
    "preview": "Aperçu",
    "reviewApproval": "Approbation de la revue",
    "lazyLoad": "Charge pénible",
    "sortBy": "Trier par",
    "reviewsPerPage": "Avis par page",
    "loadReviews": "Charger les avis",
    "collectionShowing": "Affichage de la collection",
    "hideEmptyRatings": "Cacher les notes vides",
    "questionApproval": "Approbation de la question",
    "answerApproval": "Approbation de la réponse",
    "questionsPerPage": "Questions par page",
    "theme": "Thème",
    "removeBorderInReviewItem": "Supprimer la bordure dans la révision de l'élément",
    "displayOneColumnReviewOnMobile": "Afficher la revue d'une colonne sur le mobile",
    "autoplay": "Lecture automatique",
    "autoPlaySpeedInMilliseconds": "Vitesse de lecture automatique en millisecondes",
    "autoHeight": "Hauteur automatique",
    "headerLayout": "Mise en page de l'en-tête",
    "ryviuSidebarWidget": "Widget de la barre latérale Ryviu",
    "offsetSidebar": "Barre latérale de décalage",
    "popUp": "Pop up",
    "position": "Position",
    "background": "Arrière-plan",
    "activeColor": "Actif",
    "inactiveColor": "Inactif",
    "colorTitle": "Titre de la couleur",
    "backgroundButton": "Bouton d'arrière-plan",
    "colorButton": "Bouton de couleur",
    "mainColor": "Couleur principale",
    "baseSize": "Taille de base",
    "fontFamily": "Famille de police",
    "header": "En-tête",
    "filterAndSortReviews": "Filtrer et trier les avis",
    "writeReview": "Écrire un commentaire",
    "reviewerDetails": "Détails de l'évaluateur",
    "reviewDetails": "Détails de la révision",
    "reviewContentDisplay": "Réviser l'affichage du contenu",
    "reviewEngagement": "Revoir l'engagement",
    "popupImage": "Image popup",
    "featuredItem": "Élément en vedette",
    "writeAReviewForm": "Écrire un formulaire de commentaire",
    "multipleImagesOnReview": "Plusieurs images en revue",
    "autoHeightImages": "Hauteur automatique des images",
    "effectsWhenHoveringImages": "Effets lors du survol des images",
    "yourLanguage": "Votre langue",
    "reviewsWidget": "Widget de commentaires",
    "button": "Bouton",
    "verifyIcon": "Vérifier l'icône",
    "popup": "Popup",
    "form": "Forme",
    "avatar": "Avatars",
    "filter": "Filtre",
    "sortByCheckbox": "Trier par",
    "writeAReview": "Écrire un avis",
    "uploadVideo": "Charger une vidéo",
    "authorName": "Nom de l'auteur",
    "reviewImages": "Revoir les images",
    "verifiedIcon": "Icône vérifiée",
    "dateTime": "Date et heure",
    "reviewTitle": "Titre de l'avis",
    "comment": "Commenter",
    "fullContent": "Contenu complet",
    "reaction": "Réaction",
    "reviewOnPopupImage": "Réviser sur l'image popup",
    "productInfo": "Informations sur le produit",
    "customerNameFormat": "Format du nom du client",
    "dateFormat": "Format de la date",
    "randomColor": "Couleur aléatoire",
    "showOnlyTextAvatars": "Afficher uniquement les avatars de texte",
    "previewSpecificSettingsNote": "Les paramètres spécifiques aux aperçus n'affectent pas l'affichage des couleurs de votre boutique.",
    "latest": "Dernier",
    "oldest": "Plus ancien",
    "highestRating": "Note la plus élevée",
    "lowestRating": "Notation la plus basse",
    "loadMoreButton": "Charger plus de bouton",
    "infiniteScroll": "Défilement infini",
    "mostHelpful": "Le plus utile",
    "newest": "Plus récent",
    "masonry": "Maçonnerie",
    "disabled": "Désactivé",
    "ms": "Mms",
    "helpText": {
      "reviewApproval": "Exiger l'approbation avant que les avis soient publiés",
      "lazyLoad": "Charger les avis quand ils arrivent en vue",
      "collectionShowing": "Afficher la note des étoiles sur la page de la collection",
      "hideEmptyRatings": "Ne pas afficher les notes d'étoiles sur la page de la collection s'il n'y a pas d'avis",
      "questionApproval": "Exiger l'approbation avant la publication des questions",
      "answerApproval": "Exiger une approbation avant que les réponses soient publiées"
    },
    "questionApprovalHelp": "Approuver les Q&A à afficher sur le site",
    "questionsPerPageHelp": "Le nombre maximum de questions par page est de 20",
    "buttonBackground": "Arrière-plan du bouton",
    "buttonColor": "Couleur du bouton",
    "createdTime": "Date de création",
    "askTheCommunity": "Demander à la communauté",
    "answer": "Répondre",
    "votes": "Votes",
    "askCommunityBlock": "Demander le bloc de la communauté",
    "askCommunity": "Demander à la communauté",
    "textAskButton": "Bouton de demande de texte",
    "headerSection": "Section d'en-tête",
    "headerTitle": "Titre de l'en-tête",
    "customerPage": "Page client",
    "searchBar": "Barre de recherche",
    "placeholderSearchInput": "Saisie de recherche des espaces réservés",
    "noQuestion": "Pas de question",
    "questionsNotFound": "Aucune question trouvée",
    "showing": "Affichage en cours",
    "of": "de",
    "question": "Question",
    "questions": "Questions",
    "questionItem": "Élément de question",
    "vote": "Voter",
    "total": "Total",
    "answers": "Réponses",
    "seeAll": "Tout voir",
    "answerItem": "Élément de réponse",
    "shopOwner": "Propriétaire de la boutique",
    "questionForm": "Formulaire de question",
    "titleForm": "Formulaire de titre",
    "titleFormAskQuestion": "Formulaire de titre pour poser une question",
    "descriptionForm": "Formulaire de description",
    "nameField": "Champ de nom",
    "yourName": "Votre nom",
    "namePlaceholder": "Nom du champ texte : espace réservé",
    "emailField": "Champ email",
    "yourEmail": "Votre adresse e-mail",
    "emailPlaceholder": "Espace réservé pour le champ texte de l'e-mail",
    "questionField": "Champ de question",
    "yourQuestion": "Votre question",
    "questionPlaceholder": "Espace réservé à la question du champ de texte",
    "sendAQuestion": "Envoyer une question",
    "successMessage": "Message de réussite",
    "sendQuestionSuccess": "Envoi de la question réussi",
    "errorMessage": "Message d'erreur",
    "sendQuestionError": "Erreur d'envoi de la question",
    "answerForm": "Formulaire de réponse",
    "answerTitleForm": "Formulaire de titre de réponse",
    "questionLabelForm": "Formulaire d'étiquette de question",
    "answerField": "Champ de réponse",
    "yourAnswer": "Votre réponse",
    "answerPlaceholder": "Espace réservé pour la réponse au champ texte",
    "submitAnswer": "Soumettre la réponse",
    "sendReplySuccess": "Envoi de la réponse réussi",
    "sendReplyError": "Erreur d'envoi de la réponse",
    "textErrorOnAnswerForm": "Erreur de texte sur le formulaire de réponse",
    "answersList": "Liste des réponses",
    "on": "À propos de",
    "error": {
      "maxValue50": "La valeur maximale est de 50"
    },
    "leftSide": "Côté gauche",
    "rightSide": "Côté droit",
    "withReviews": "Avec avis",
    "withoutReviews": "Sans avis",
    "withQuestions": "Avec questions",
    "withoutQuestions": "Sans questions",
    "featuredMasonry": "Maçonnerie en vedette",
    "featuredCarousel": "Carrousel en vedette",
    "showPreviewWithReviews": "Afficher l'aperçu avec les avis",
    "showPreviewWithoutReviews": "Afficher l'aperçu sans avis",
    "chooseWidgetLanguageForReviews": "Choisir la langue du widget pour les avis",
    "chooseWidgetLanguageForQuestions": "Choisir la langue du widget pour les questions",
    "reviewTotalTexts": "avis",
    "border": "Border",
    "padding": "Padding",
    "style": "Style",
    "size": "Taille",
    "none": "Aucun",
    "dotted": "Pointillé",
    "dashed": "Tiret",
    "solid": "Solid",
    "double": "Double",
    "groove": "Groove",
    "ridge": "Crête",
    "inset": "Inset",
    "outset": "Début",
    "top": "En haut",
    "right": "Droite",
    "bottom": "Bas",
    "left": "Gauche",
    "ratingDefault": "Notation par défaut",
    "ratingDefaultForWriteForm": "Notation par défaut pour le formulaire d'écriture.",
    "icon": "Icône",
    "resizeImageToFitContainer": "Redimensionner l'image pour l'adapter à son conteneur.",
    "cover": "Couverture",
    "contain": "Contient",
    "headerV1": "En-têteV1",
    "enable": "Activer",
    "bottomLeft": "En bas à gauche",
    "horizontal": "Horizontal",
    "fifty": "50",
    "configureCustomerNameFormat": "Configurer le format d'affichage des noms de clients dans les avis",
    "monthDdYyyy": "Mois jj, aaaa",
    "mthYyyy": "Mth yyyy",
    "ddMmYy": "jj/mm/aa",
    "dMyyyy": "dd/m/aaaa",
    "mmDdYyyy": "jj/mm/aaaa",
    "ddMmYyyy": "jj.mm.aaaa",
    "yyyyMmD": "aaaa-mm-jj",
    "oneYearAgo": "Il y a 1 an",
    "topRight": "En haut à droite",
    "topLeft": "En haut à gauche",
    "bottomRight": "En bas à droite",
    "center": "Centrer",
    "vertical": "Vertical",
    "modern": "Moderne",
    "widgets": {
      "productReviews": {
        "title": "Avis sur les produits",
        "description": "Présentez les avis détaillés des clients sur vos pages de produits pour établir la confiance et améliorer les taux de conversion."
      },
      "totalRatings": {
        "title": "Total des évaluations",
        "description": "Affichez le résumé global de l'évaluation des produits sur vos pages de produits et de collections pour des aperçus rapides des clients."
      },
      "featuredReviews": {
        "title": "Surligner les avis en vedette",
        "description": "Affichez les avis des clients sélectionnés dans n'importe quelle section de votre site pour mettre en valeur les commentaires les plus impactés et construire la crédibilité."
      },
      "quickAccess": {
        "title": "Bouton d'accès rapide aux avis",
        "description": "Donnez un accès instantané aux avis en vedette avec un bouton dédié sur n'importe quelle section de votre site."
      },
      "realtimeAlerts": {
        "title": "Alertes de revue en temps réel",
        "description": "Informer instantanément les clients des nouveaux avis de produits avec un déclencheur popup."
      },
      "reviewBadge": {
        "title": "Revoir le badge",
        "description": "Pour augmenter la confiance et la visibilité, ajoutez un badge affichant l'évaluation de votre produit dans n'importe quelle section de votre site."
      },
      "qaSection": {
        "title": "Section Q&A client",
        "description": "Les clients peuvent poser des questions et consulter les réponses directement sur vos pages produits, en améliorant l'engagement des clients."
      }
    },
    "banner": {
      "title": "Vous devez ajouter un noyau Ryviu à votre thème !",
      "description": "Pour utiliser pleinement les fonctionnalités et les paramètres de Ryviu sur votre boutique, veuillez activer l'App Intégrée Ryviu. Cliquez sur le bouton « Activer l'application intégrée » ci-dessous, puis cliquez sur Enregistrer."
    }
  },
  "emails": {
    "title": "Abonnements par e-mail",
    "emailAutomation": "Email automation",
    "emailNotification": "Notification par e-mail",
    "email": "Courriel",
    "queueStatus": "Statut de la file d'attente",
    "orderId": "ID de la commande",
    "readAt": "Lire le",
    "createdAt": "Créé le",
    "sendEmail": "Envoyer un e-mail",
    "deleteSelected": "Supprimer la sélection",
    "unverified": "Non vérifié",
    "pending": "En attente",
    "sent": "Envoyé",
    "failed": "Echoué",
    "unknown": "Inconnu",
    "waiting": "En attente",
    "scheduled": "Planifié",
    "cancelled": "Annulé",
    "notRead": "Non lu",
    "pleaseSelectEmail": "Veuillez sélectionner au moins un email",
    "emailsDeletedSuccess": "E-mails supprimés avec succès",
    "emailsSentSuccess": "E-mails envoyés avec succès",
    "errorDeletingEmails": "Erreur lors de la suppression des e-mails",
    "errorSendingEmails": "Erreur lors de l'envoi des e-mails",
    "singular": "Email",
    "plural": "E-mails",
    "deletingEmail": "Suppression de l'e-mail...",
    "deleteEmails": "Supprimer les E-mails",
    "deleteEmail": "Supprimer l'e-mail",
    "totalTooltip": "Le nombre total d'e-mails.",
    "sentTooltip": "Le nombre total d'emails envoyés.",
    "scheduledTooltip": "Le nombre total d'emails programmés.",
    "openedTooltip": "Le nombre total d'e-mails ouverts.",
    "ratedTooltip": "Le nombre total d'emails notés.",
    "failedTooltip": "Le nombre total d'emails échoués.",
    "notSendTooltip": "Le nombre total d'e-mails annulés.",
    "upgradeBanner": {
      "title": "Mettre à niveau pour débloquer les fonctionnalités de messagerie",
      "desc": "L'envoi d'e-mails est exclusivement disponible pour les forfaits payants. Mettez à niveau votre compte maintenant pour envoyer des e-mails directement depuis l'application et augmentez votre engagement client sans effort.",
      "upgradeNow": "Mettre à niveau maintenant",
      "learnMore": "En savoir plus"
    }
  },
  "dashboard": {
    "title": "Tableau de bord",
    "overview": "Aperçu",
    "statistics": "Statistiques",
    "recentActivity": "Activité récente",
    "quickActions": "Actions rapides",
    "totalReviews": "Total des commentaires",
    "totalProducts": "Total des produits",
    "totalQuestions": "Total des questions",
    "totalWidgets": "Total des Widgets",
    "pendingReviews": "Avis en attente",
    "pendingQuestions": "Questions en attente",
    "recentReviews": "Avis récents",
    "recentQuestions": "Questions récentes",
    "topProducts": "Meilleurs produits",
    "performance": "Performances",
    "analytics": "Analyses",
    "reports": "Rapports",
    "insights": "Aperçus",
    "trends": "Tendances",
    "growth": "Croissance",
    "conversion": "Conversion",
    "engagement": "Engagement",
    "satisfaction": "Satisfaction",
    "rating": "Évaluation",
    "averageRating": "Notation moyenne",
    "responseRate": "Taux de réponse",
    "responseTime": "Temps de réponse",
    "customerSatisfaction": "Satisfaction du client",
    "productPerformance": "Performance du produit",
    "reviewPerformance": "Revoir les performances",
    "questionPerformance": "Performance de la question",
    "static": "Statique",
    "sales": "Ventes",
    "reviews": "Revues",
    "questions": "Questions",
    "orders": "Commandes",
    "emails": "E-mails",
    "reviewsTooltip": "Le nombre total de commentaires",
    "questionsTooltip": "Le nombre total de questions",
    "emailsTooltip": "Nombre total d'emails",
    "needHelp": "Besoin d'aide ?",
    "liveChat": "Chat en direct",
    "liveChatContent": "Nous sommes disponibles du lundi au vendredi, de 8 h à 17 h (GMT+7).",
    "emailSupport": "Envoyer un e-mail à l'assistance",
    "emailSupportContent": "Votre courriel sera généralement adressé dans les 12 à 24 heures ouvrables.",
    "emailUs": "Envoyez-nous un e-mail",
    "helpCenter": "Centre d'aide",
    "helpCenterContent": "Consultez nos guides étape par étape et nos articles de dépannage.",
    "ourDocument": "Notre document",
    "whatNewsTitle": "Personnalisez la disposition de votre widget de revue.",
    "whatNewsDescription": "Apprenez à modifier et personnaliser facilement la mise en page de votre widget de revue. Ajustez les styles, les polices et les couleurs pour correspondre au design et à la marque de votre boutique. Suivez notre guide étape par étape pour rendre votre widget parfait pour vos clients.",
    "learnMore": "En savoir plus",
    "recommendedApps": "Applications recommandées",
    "retonContent": "Gagnez de la fidélité avec des points, des réductions et des avantages VIP exclusifs.",
    "ryviuContent": "Importez des produits Amazon dans votre boutique Shopify en toute simplicité.",
    "lookfyContent": "La solution ultime pour créer des livres d'apparence et des galeries de produits.",
    "annifyContent": "Engagez vos clients instantanément avec les barres d'annonce attractives.",
    "reviewed": "Révisé",
    "newQuestion": "Nouvelle question",
    "likedReview": "Avis aimé",
    "dislikedReview": "Revue non aimée",
    "replied": "Répondu",
    "likedQuestion": "Question aimée",
    "dislikedQuestion": "Question non aimée",
    "liked": "Aimé",
    "disliked": "Non aimé"
  },
  "integrations": {
    "title": "Intégration de l'application Shopify",
    "description": "Augmentez le taux de conversion lorsque vous utilisez une application intégrée",
    "totalApps": "Total des applications {{count}} Shopify",
    "addIntegration": "Demande d'intégration",
    "descriptions": {
      "ecomposer": "Construire des pages d'accueil, de produits, de pages de collecte, etc. axées sur la conversion.",
      "lookify": "La solution ultime pour créer des livres d'apparence et des galeries de produits.",
      "cross-sell-upsell": "Conduisez des ventes avec des ventes croisées sur mesure, des ventes, des Pop-ups et des Bundles dans 8 pages stratégiques sur votre boutique Shopify !",
      "easy-tabs": "Shopify onglets de la page des produits. Organisez les descriptions, les avis et les tailles des produits dans des onglets en apparence pro.",
      "searchpie": "Rev up sales, site view & search rankings with comprehensive auto-SEO tool.",
      "frequently-bought": "Offrez des produits et dégustez le pouvoir de la vente incitative avec des recommandations personnalisées et des remises.",
      "also-bought": "Des recommandations de produits premium pour augmenter vos ventes grâce à la découverte de produits et de ventes croisées.",
      "agile-theme": "Thème Top Shopify pour un design élégant, des performances rapides et des outils de conversion efficaces.",
      "json-ld": "Optimisez votre trafic SEO en mettant en évidence vos commentaires, prix et détails commerciaux dans les résultats de recherche.",
      "foxify": "Ventes d’impact, coûts et bénéfices à la fois grâce à plus de 80 conceptions à haute conversion et analyses avancées.",
      "lantern": "Créez des quiz qui transforment les clients de fenêtres en acheteurs sûrs. Réservez une consultation de quiz GRATUITE.",
      "zeno": "Créez facilement des pages et des sections de thème qui peuvent faire ressortir votre boutique et augmenter vos ventes.",
      "beae": "Construire un produit flexible, la collecte, la page d'accueil, l'atterrissage, le contact. Gratuit pour l'installation.",
      "bss-labels": "Lancez un magasin à haute conversion avec des étiquettes de confiance et des badges.",
      "pagefly": "Créer une page d'accueil des ventes, page des produits pour la saison des vacances.",
      "flash-search": "Recherche & Filtre alimenté par les IA, Merchandising, Analytics, OS 2.0",
      "product-filter": "Filtres de produits avancés et recherche intelligente pour des ventes élevées",
      "sales-popup": "Augmentez les ventes Popup Achats & Commandes récentes pour la preuve sociale",
      "neat-theme": "Sur mesure pour les marques de contes visuels, offrant des fonctionnalités de personnalisation et de merchandising faciles.",
      "qikify": "Popup de vente, prof social, newsletter popup, notification de vente",
      "veda": "Créez sans effort des pages époustouflantes et stimulantes pour les ventes qui attirent les visiteurs avec un code zéro.",
      "parcel-panel": "Synchronisation automatique, suivi et mise à jour, page de suivi de marque, notifications d'expédition, upsell.",
      "seo-optimizer": "Booster SEO, Texte Alt, Balises Meta, Pagespeed, Service Expert",
      "layouthub": "Créer des pages de destination, de produit et de blog en moins de 10 minutes",
      "ava-email": "SMS, Email Marketing, Pop up, Klaviyo, Privé, Mailchimp alt",
      "gempages": "GemPages: CRO constructeur de pages avec l'entonnoir de vente à convertir."
    }
  },
  "startGuide": {
    "title": "Démarrer le tutoriel",
    "description": "Utilisez ce guide personnalisé pour faire fonctionner votre boutique.",
    "tasksCompleted": "Les tâches {{completed}} sur {{total}} ont été complétées",
    "dismiss": "Refuser",
    "markAsDone": "Marquer comme fait",
    "markAsNotDone": "Marquer comme non fait",
    "steps": {
      "display": {
        "title": "À afficher",
        "description": "Ajoutez Ryviu à votre thème Ryviu widgets, activez le noyau Ryviu dans les paramètres de votre thème. Cliquez sur « Ajouter», puis « Enregistrer» et revisitez cette page pour confirmer l’activation.",
        "addNow": "Ajouter maintenant",
        "check": "Contrôler"
      },
      "showing": {
        "title": "Affichage des widgets Ryviu",
        "description": "Pour afficher les widgets Ryviu, il suffit de naviguer vers la page des widgets et de suivre les instructions fournies.",
        "widgetsPage": "Page des widgets"
      },
      "pickPlan": {
        "title": "Choisissez un plan",
        "description": "Vous pouvez modifier votre plan de compte pour mieux répondre aux besoins de votre magasin avec divers paquets de support disponibles.",
        "moreDetails": "Plus de détails"
      }
    }
  },
  "menu": {
    "home": "Domicile",
    "products": "Produits",
    "reviews": "Revues",
    "emails": "E-mails",
    "questions": "Q&A",
    "widgets": "Widgets",
    "partners": "Partenaires",
    "pricing": "Tarification",
    "settings": "Réglages"
  },
  "subscription": {
    "title": "Sélectionnez un plan",
    "currentSubscription": "Abonnement actuel",
    "currentPlanMessage": "Vous êtes actuellement sur le plan {{planName}}.",
    "monthly": "Mensuel",
    "annually": "Annuellement",
    "save25Percent": "-25%",
    "confirmPlan": "Confirmez votre abonnement",
    "billingCycle": "Cycle de facturation",
    "billingCycleDescription": "Choisissez la fréquence à laquelle vous souhaitez être facturé. Vous pouvez annuler à tout moment.",
    "monthlyBilling": "Mensuel",
    "yearlyBilling": "Annuel",
    "payMonthly": "Payer {{price}}/mois",
    "payYearly": "{{price}}/mois - payer {{yearlyPrice}} ({{monthlyPrice}} × 12 mois)",
    "saveAmount": "Enregistrer {{amount}}",
    "billedEvery30Days": "facturés tous les 30 jours",
    "discount": "Remise",
    "enterDiscountCode": "Entrez le code de réduction",
    "apply": "Appliquer",
    "discountApplied": "{{percent}}% appliqué",
    "discountForMonths": "Save {{percent}}% for first {{months}} month",
    "discountForMonths_plural": "Save {{percent}}% for first {{months}} months",
    "removeDiscount": "Supprimer la remise",
    "planSummary": "Forfait",
    "changePlan": "Changer de plan",
    "planDescription": "Vous pouvez modifier ou annuler votre forfait à tout moment.",
    "total": "Total",
    "next": "Suivant",
    "back": "Précédent",
    "fullListOfFeatures": "+ Liste complète des fonctionnalités",
    "closeFullListOfFeatures": "− Fermer la liste complète des fonctionnalités",
    "frequentlyAskedQuestions": "Foire aux questions",
    "seeMorePricing": "En savoir plus sur",
    "pricingComparison": "comparaison des prix",
    "easyStartFree": "Démarrage facile, gratuit avec les fonctionnalités essentielles.",
    "everythingSimpler": "Tout est plus simple avec un support avancé.",
    "driveMoreSales": "Conduisez plus de ventes avec plus de fonctionnalités.",
    "saveMoreTime": "Gagnez plus de temps avec le support multi-sources",
    "freeForever": "Gratuit pour toujours",
    "billedMonthly": "Facturé mensuellement",
    "billedYearly": "Facturé chaque année",
    "perMonth": "mois",
    "discountCode": "Code de réduction",
    "today": "Aujourd'hui",
    "currency": "USD",
    "chooseFree": "Choisir Gratuit",
    "chooseBasic": "Choisir Basique",
    "chooseAdvanced": "Choisir Avancé",
    "chooseUnlimited": "Choisir un nombre illimité",
    "currentPlan": "Abonnement actuel",
    "daysFreeTrial": "{{days}} jours d'essai gratuit",
    "features": {
      "limit20Reviews": "Limiter 20 avis pour chaque 50 produits",
      "productReviewsWidget": "Widget de commentaires de produits",
      "importReviewsTools": "Importer les avis",
      "importedSourceAliexpress": "Source importée : Aliexpress",
      "liveChat": "Chat en direct",
      "allInFreePlan": "Tout en plan gratuit",
      "limit200Reviews": "Limiter 200 avis pour chaque 400 produits",
      "featuredReviews": "Avis en vedette",
      "questionsAnswers": "Questions et réponses",
      "emailRequestReviews": "Envoyer par e-mail les commentaires de la demande",
      "importedSourcesAmazonCsv": "Sources importées : +Amazon, CSV",
      "allInBasicPlan": "Tout dans le plan Basique",
      "limit500Reviews": "Limiter 500 avis pour chaque 1000 produits",
      "importSourcesEtsyDHgateWalmart": "Importer des sources: + Etsy, DHgate, Walmart.com",
      "fullyCustomizedLayout": "Options de mise en page entièrement personnalisées",
      "allInAdvancedPlan": "Tout dans le plan avancé",
      "unlimitedReviews": "Avis illimités",
      "importMultipleSources": "Importer les avis à partir de plusieurs sources pour un produit",
      "videoReview": "Revue vidéo",
      "productReviewsFeed": "Fil des commentaires sur le produit (XML)",
      "exportBulkReviews": "Exporter les avis en vrac (CSV)",
      "allGrowthFeatures": "Toutes les fonctionnalités de croissance"
    },
    "faq": {
      "freePlanQuestion": "Qu'est-ce qui est inclus dans le forfait gratuit ?",
      "freePlanAnswer": "Notre plan gratuit comprend des fonctionnalités essentielles telles que l'affichage de commentaires, l'ajout de photos de révision et les options de personnalisation de base, idéal pour les petits magasins qui commencent avec les commentaires.",
      "switchPlansQuestion": "Puis-je changer de forfait à tout moment ?",
      "switchPlansAnswer": "Oui ! Vous pouvez mettre à niveau ou rétrograder votre plan quand vous en avez besoin. Les changements entreront en vigueur immédiatement, et vous ne serez facturé que pendant la durée de chaque forfait.",
      "trialPeriodQuestion": "Existe-t-il une période d'essai pour les régimes primes?",
      "trialPeriodAnswer": "Oui, nous vous offrons une période d'essai pour explorer nos fonctionnalités premium. Vous pouvez tester les fonctionnalités et voir comment elles ont un impact sur votre boutique avant de vous engager.",
      "billingQuestion": "Comment fonctionne la facturation ?",
      "billingAnswer": "La facturation est mensuelle ou annuelle, selon vos préférences. La facturation annuelle offre une réduction par rapport à la facturation mensuelle.",
      "cancelQuestion": "Puis-je annuler mon abonnement ?",
      "cancelAnswer": "Absolument ! Vous pouvez annuler à tout moment directement dans les paramètres de votre compte. Une fois annulé, vous conserverez l'accès aux fonctionnalités de votre forfait jusqu'à la fin de votre cycle de facturation.",
      "additionalFeesQuestion": "Y a-t-il des frais supplémentaires?",
      "additionalFeesAnswer": "NON ! Tous les frais sont inclus dans le coût de l'abonnement. Il n'y a pas de frais cachés ou de frais de transaction supplémentaires.",
      "helpDecidingQuestion": "Que se passe-t-il si j'ai besoin d'aide pour décider quel plan me convient le mieux ?",
      "helpDecidingAnswer": "Si vous n'êtes pas sûr, notre équipe est là pour vous aider ! Il vous suffit de nous contacter par chat ou par e-mail, et nous vous guiderons vers la meilleure option pour vos besoins."
    },
    "comparison": {
      "pricing": "Tarification",
      "payMonthly": "Payer mensuellement",
      "payYearly": "Payer chaque année (économisez jusqu'à 25%)*",
      "reviewImporter": "Examiner l'importateur",
      "reviewsPerProduct": "Avis par produit",
      "totalProducts": "Total des produits",
      "importedSources": "Sources importées",
      "importMultipleSources": "Importer plusieurs sources",
      "syncNewReviews": "Synchroniser les nouveaux avis",
      "displayWidget": "Afficher le Widget",
      "productReviewsWidget": "Widget de commentaires de produits",
      "featuredReviews": "Avis en vedette",
      "boostSalesPopup": "Boost de la fenêtre de ventes",
      "questionsAnswers": "Questions et réponses",
      "googleRichSnippet": "Snippet Google Rich",
      "customizationWidget": "Widget de personnalisation",
      "customizeDesign": "Personnaliser le design",
      "masonryLayout": "Disposition de maçonnerie",
      "carouselLayout": "Disposition du carrousel",
      "lazyLoadWidget": "Charger le widget",
      "removeLogoBranding": "Supprimer le marquage du logo",
      "photoReview": "Revue photo",
      "translateWidget": "Traduire le widget",
      "requestReviews": "Demander des avis",
      "emailRequestReviews": "Envoyer par e-mail les commentaires de la demande",
      "importExport": "Importer/Exporter",
      "importExportReviewsCsv": "Importer/Exporter les avis CSV",
      "importExportQaCsv": "Importer/Exporter Q&A CSV",
      "productReviewsFeedXml": "Fil des commentaires sur le produit (XML)",
      "exportBulkReviewsCsv": "Exporter les avis en vrac (CSV)",
      "support": "Soutien",
      "liveChat": "Chat en direct"
    },
    "success": "Abonnement créé avec succès",
    "error": "Erreur",
    "switchedToFree": "Passage à l'offre gratuite réussi"
  },
  "customizeEmail": {
    "title": "Personnaliser l'e-mail",
    "sendTestEmail": "Envoyer un e-mail de test",
    "general": "Généraux",
    "subject": "Sujet",
    "colors": "Couleurs",
    "background": "Arrière-plan",
    "customizeSections": "Personnaliser les sections",
    "customize": "Personnaliser",
    "backToSections": "Retour aux sections",
    "showHeader": "Afficher l'en-tête",
    "headerBackground": "Arrière-plan de l'en-tête",
    "logo": "Logo",
    "currentLogo": "Logo actuel",
    "changeLogo": "Changer le logo",
    "uploadLogo": "Télécharger le logo",
    "logoSize": "Taille du logo",
    "width": "Width",
    "height": "Hauteur",
    "align": "Align",
    "lineColor": "Couleur de ligne",
    "removeSection": "Supprimer la section",
    "buttonText": "Texte du bouton",
    "textColor": "Couleur du texte",
    "showFooter": "Afficher le pied de page",
    "footerBackground": "Arrière-plan du pied de page",
    "contentFooter": "pied de page du contenu",
    "enterFooterContent": "Entrez le contenu du pied de page ici...",
    "unsubscribeLinkText": "Texte du lien de désinscription",
    "text": "Texte du texte",
    "starColor": "Couleur des étoiles",
    "orderItems": "Articles de la commande",
    "orderItemsDescription": "Cette section affichera la liste des produits dans votre commande.",
    "content": "Contenus",
    "enterContent": "Entrez votre contenu ici...",
    "fontWeight": "Poids de la police",
    "normal": "Normale",
    "bold": "Bold",
    "image": "Image",
    "sectionImage": "Image de section",
    "changeImage": "Changer l'image",
    "uploadImage": "Charger une image",
    "imageSize": "Taille de l'image",
    "acceptImageTypes": "Accepter .jpg, .png, .webp et max 2Mo",
    "save": "Enregistrer",
    "discard": "Abandonner",
    "templateSaved": "Modèle enregistré avec succès",
    "errorSavingTemplate": "Erreur lors de la sauvegarde du modèle : {{error}}",
    "sendTestEmailModal": "Envoyer un e-mail de test",
    "enterEmailAddress": "Entrez une adresse e-mail pour envoyer un e-mail de test avec votre modèle actuel :",
    "emailAddress": "Adresse e-mail",
    "sending": "Envoi...",
    "send": "Envoyer",
    "cancel": "Abandonner",
    "testEmailSentSuccess": "E-mail de test envoyé avec succès à",
    "pleaseEnterValidEmail": "Veuillez entrer une adresse e-mail valide.",
    "uploadingImage": "Envoi de l'image...",
    "back": "Précédent",
    "left": "Gauche",
    "center": "Centrer",
    "right": "Droite",
    "show": "Afficher",
    "hide": "Cacher",
    "availableSections": {
      "image": "Image",
      "text": "Texte du texte",
      "orderItems": "Articles de la commande",
      "rateList": "Liste des tarifs",
      "button": "Bouton",
      "line": "Lignes"
    },
    "sections": {
      "header": "En-tête",
      "footer": "Pied de page",
      "line": "Lignes",
      "button": "Bouton",
      "rating": "Évaluation",
      "text": "Texte du texte",
      "image": "Image",
      "customerName": "Nom du client",
      "thankYou": "Merci",
      "message": "Message"
    },
    "ratingTexts": {
      "terrible": "Terrible",
      "poor": "Mauvais",
      "average": "Moyenne",
      "veryGood": "Très bon",
      "excellent": "Excellent"
    }
  },
  "emailAutomation": {
    "title": "Révision de la demande d'e-mail",
    "backToEmail": "Courriel",
    "customizeEmail": "Personnaliser l'e-mail",
    "sendAutomatically": "Envoyer automatiquement les e-mails de révision de demande",
    "webhooksConfiguration": "Configuration des Webhooks",
    "webhooksDescription": "Ceci créera des webhooks pour les événements ORDERS_CREATE et ORDERS_UPDATED dans votre boutique Shopify.",
    "sendAfter": "Envoyer après",
    "oneHour": "1 heure",
    "sixHours": "6 heures",
    "tenHours": "10 heures",
    "twentyFourHours": "24 heures",
    "custom": "Personnalisé",
    "timeDelay": "Délai",
    "timeUnit": "Unité de temps",
    "days": "Jours",
    "hours": "heures",
    "whenOrderStatus": "Quand l'état de la commande",
    "purchased": "Acheté",
    "fulfilled": "Accompli",
    "delivered": "Livré",
    "afterReviewSubmitted": "Après vérification soumise",
    "redirectToCustomizeUrl": "Rediriger vers la personnalisation de l'URL",
    "customizeUrl": "Personnaliser l'URL",
    "thankYouPage": "Page de remerciement",
    "thankYouPageDescription": "Configurez la page de remerciement avec un code de réduction.",
    "thankYouPageLink": "page de remerciement",
    "updatingSettings": "Mise à jour des paramètres d'automatisation des e-mails...",
    "settingsSaved": "Paramètres enregistrés avec succès",
    "settingsError": "Erreur lors de l'enregistrement des paramètres",
    "webhooksCreated": "Webhooks créés avec succès",
    "webhooksRemoved": "Webhooks supprimés avec succès",
    "webhooksError": "Erreur de gestion des webhooks"
  },
  "emailNotifications": {
    "title": "Notification par e-mail",
    "backToEmail": "Courriel",
    "type": "Type de texte",
    "name": "Nom",
    "pendingDomainVerification": "En attente de vérification de domaine",
    "pendingDomainDescription": "You have {{count}} domain(s) waiting to be verified: {{domains}}.",
    "pendingDomainInstructions": "Veuillez compléter le processus de vérification en ajoutant les enregistrements DNS requis. Allez dans la section Vérification de domaine ci-dessous et cliquez sur le bouton Vérifier le domaine pour voir les enregistrements DNS requis.",
    "emailVerificationRequired": "Vérification d'email requise",
    "emailVerificationInProgress": "Vérification de l'e-mail en cours",
    "emailVerificationDescription": "Cet e-mail doit être vérifié avec AWS SES avant que vous puissiez l'utiliser pour envoyer des e-mails. Cliquez sur \"Vérifier l'e-mail\" pour commencer le processus de vérification.",
    "emailVerificationSent": "Un e-mail de vérification a été envoyé à {{email}}. Veuillez vérifier votre boîte de réception et cliquez sur le lien de vérification.",
    "saveToVerify": "Cliquez sur Enregistrer en haut de la page pour enregistrer et vérifier cet e-mail",
    "senderEmail": "E-mail de l'expéditeur",
    "fromEmail": "De l'e-mail",
    "fromDomain": "Depuis le domaine",
    "fromDomainHelpText": "La partie du domaine de votre email d'expéditeur (par exemple 'example.com')",
    "fromName": "De nom",
    "verifyEmail": "Vérifier l'e-mail",
    "checkAgain": "Vérifier à nouveau",
    "verifyingEmail": "Vérification de l'e-mail...",
    "checkingVerification": "Vérification de la vérification...",
    "domainVerification": "Vérification du domaine",
    "domainVerificationDescription": "Vérifiez votre domaine avec AWS SES pour envoyer des emails depuis votre domaine.",
    "pendingDomains": "Domaines en attente",
    "domainsWaitingForVerification": "Domaines en attente de vérification",
    "viewDnsRecords": "Voir les enregistrements DNS",
    "checkStatus": "Vérifier le statut",
    "domainToVerify": "Domaine à vérifier",
    "domainToVerifyHelpText": "Entrez votre domaine sans 'www', par exemple 'example.com'",
    "domainVerified": "Domaine vérifié",
    "domainVerifiedDescription": "Le domaine {{domain}} a été vérifié avec succès.",
    "dkim": "DKIM",
    "mailFrom": "ENVOYER À PARTIR DE L'ENVOYAGE",
    "verified": "Vérifié",
    "notVerified": "Non vérifié",
    "pending": "En attente",
    "refreshVerificationStatus": "Rafraîchir le statut de vérification",
    "checkingVerificationStatus": "Vérification du statut de vérification...",
    "domainPartiallyVerified": "Domaine partiellement vérifié",
    "domainPartiallyVerifiedDescription": "Le domaine est vérifié mais la vérification DKIM est toujours en attente. Veuillez compléter la configuration DNS.",
    "checkDomainStatus": "Vérifier le statut du domaine",
    "checkingDomainStatus": "Vérification de l'état du domaine...",
    "verifyDomain": "Vérifier le domaine",
    "refreshVerification": "Rafraîchir la vérification",
    "startingVerification": "Démarrage de la vérification...",
    "saveDomainFirst": "Cliquez sur le bouton Enregistrer en haut de la page pour enregistrer ce domaine avant de vérifier",
    "domainVerificationInstructions": "Instructions de vérification de domaine",
    "addDnsRecordsDescription": "Ajoutez les enregistrements DNS suivants à votre domaine pour le vérifier avec AWS SES:",
    "dkimRecords": "Enregistrements DKIM (CNOM)",
    "customMailFromDomain": "Adresse mail personnalisée du domaine",
    "customMailFromDescription": "La mise en place d'un domaine MAIL FROM personnalisé améliore la délivrabilité des e-mails et évite les problèmes d'alignement SPF.",
    "value": "Valeur",
    "copyToClipboard": "Copier dans le presse-papiers",
    "notification": "Notification",
    "notificationDescription": "L'e-mail que votre boutique utilise pour envoyer des e-mails à vos clients.",
    "newReviewNotification": "Nouvelle notification de révision",
    "customer": "Client",
    "admin": "Administrateur",
    "disable": "Désactiver",
    "enable": "Activer",
    "savedSuccessfully": "Enregistré avec succès",
    "invalidEmail": "Adresse e-mail invalide. Veuillez corriger avant de sauvegarder.",
    "invalidDomain": "Domaine invalide. Veuillez corriger avant de sauvegarder.",
    "emailInvalid": "Email invalid",
    "domainInvalid": "Domaine invalide. Exemple: exemple.com",
    "verificationEmailSent": "E-mail de vérification envoyé à {{email}}. Veuillez vérifier votre boîte de réception.",
    "emailVerified": "Courriel vérifié",
    "emailVerifiedDescription": "Votre adresse e-mail {{email}} est vérifiée et prête à l'emploi.",
    "verificationEmailSentTitle": "E-mail de vérification envoyé",
    "verificationEmailSentDescription": "Un e-mail de vérification a été envoyé à {{email}}. Veuillez vérifier votre boîte de réception et suivez les instructions pour vérifier.",
    "verificationError": "Erreur de vérification",
    "verificationErrorMessage": "Une erreur s'est produite lors de la vérification de cet e-mail. Veuillez réessayer.",
    "domainVerifiedSuccess": "Domaine vérifié",
    "domainSaved": "Domaine enregistré",
    "savingDomain": "Enregistrement du domaine...",
    "errorSavingDomain": "Erreur lors de l'enregistrement du domaine",
    "pleaseEnterDomain": "Veuillez entrer un domaine à vérifier",
    "copiedSuccessfully": "Copié avec succès",
    "copyFailed": "Échec de la copie",
    "updatingEmailSettings": "Mise à jour des paramètres de notification par e-mail...",
    "emailSettingsSaved": "Paramètres de notification par e-mail enregistrés avec succès",
    "emailSettingsError": "Erreur lors de l'enregistrement des paramètres de notification par e-mail"
  },
  "importReviews": {
    "title": "Importer les avis par URL",
    "backToProducts": "Produits",
    "importSettings": "Importer les paramètres",
    "selectProduct": "Sélectionner un produit",
    "changeProduct": "Changer de produit",
    "noProductSelected": "Aucun produit sélectionné",
    "noProductSelectedDescription": "Veuillez sélectionner un produit de votre boutique pour importer des avis",
    "showReviews": "Afficher les avis",
    "hideReviews": "Cacher les avis",
    "dropshippingUrlList": "Liste des URL de livraison Dropbox",
    "addUrl": "Ajouter une URL",
    "pleaseSelectProductFirst": "Veuillez sélectionner un produit dans la barre latérale gauche avant d'ajouter des URL.",
    "learnMore": "En savoir plus",
    "url": "URL",
    "urlPlaceholder": "https://www.aliexpress.com/item/10050031234567890.html",
    "urlSupportText": "Supportez les URL de produit Aliexpress, Amazon, Etsy, DHgate ou Walmart .",
    "invalidUrlError": "Veuillez entrer une URL de produit valide à partir des plates-formes prises en charge",
    "pleaseEnterUrl": "Veuillez entrer une URL",
    "pleaseSelectProductFirstError": "Veuillez d'abord sélectionner un produit",
    "importReviews": "Importer les avis",
    "loadMoreReviews": "Charger plus d'avis",
    "syncNewReviews": "Synchroniser les nouveaux avis",
    "reviewsLoaded": "Avis chargés.",
    "urlAdded": "URL ajoutée.",
    "urlDeleted": "URL supprimée.",
    "failedToLoadReviews": "Impossible de charger les commentaires.",
    "noReviewsError": "Ce produit n'a pas de commentaires.",
    "failedToGetReviews": "Impossible d'obtenir les informations des avis",
    "addProduct": "Ajouter un produit",
    "searchPlaceholder": "Chercher",
    "product": "Produit",
    "products": "produits",
    "reviewsAvailable": "avis disponibles",
    "reviewsLoadedCount": "avis",
    "contactUs": "Contactez-nous",
    "dropshipProductNoReviews": "Le produit de dépôt n'a pas d'avis",
    "successfully": "Réussi :",
    "failedToImport": "Échec de l'importation :",
    "duplicatesSkipped": "Doublons ignorés:",
    "deleteUrlTitle": "Supprimer l'URL",
    "deleteUrlMessage": "Êtes-vous sûr de vouloir supprimer cette URL ? Cette action ne peut pas être annulée.",
    "deleteUrl": "Supprimer l'URL",
    "amazonLimit100Tooltip": "Limiter 100 avis par produits Amazon",
    "almostThere": "Presque là!",
    "pleaseStayOnThisPageUntilWeFinish": "Veuillez rester sur cette page jusqu'à ce que nous ayons terminé.",
    "importSuccessful": "Importation réussie",
    "reviewsImportedSuccessfully": "avis importés avec succès.",
    "youHaveReachedYourLimit": "Vous avez atteint votre limite.",
    "youHaveReachedTheImportedReviewLimit": "Vous avez atteint la limite de révision importée pour ce produit avec votre plan Ryviu.",
    "installExtension": "Installez l'extension Ryviu Chrome.",
    "installExtensionDescription": "Installez l'extension gratuite Ryviu Chrome pour importer des avis à partir d'URL.",
    "productImportLimit": "Vous avez atteint la limite du nombre de produits pouvant importer des avis sur votre plan Ryviu.",
    "notSupportSourceWithYourPlan": "Cette source n'est pas prise en charge avec votre plan Ryviu."
  },
  "productsPage": {
    "title": "Produits",
    "importReviews": "Importer les avis",
    "moreActions": "Plus d'actions",
    "exportAllReviews": "Exporter tous les avis",
    "productReviewsFeed": "Flux de commentaires sur les produits",
    "exportSuccess": "Exportation réussie.",
    "exportedBanner": "Les avis ont été exportés. Veuillez vérifier votre email pour télécharger les avis csv fichier.",
    "exportedBannerText": "Les avis ont été exportés. Veuillez vérifier votre email pour télécharger les avis csv fichier.",
    "noProductsSelected": "Aucun produit sélectionné.",
    "showReviews": "Afficher les avis",
    "hideReviews": "Cacher les avis",
    "hasReviews": "A des avis",
    "hasQuestions": "A des questions",
    "image": "Image",
    "titleCol": "Titre de la page",
    "reviews": "Revues",
    "qa": "Q&A",
    "reviewsStatus": "État des avis",
    "viewProduct": "Voir le produit sur votre boutique",
    "exportReviewsCsv": "Exporter les avis CSV",
    "googleFeed": "Flux Google",
    "duplicate": "Duplicate",
    "duplicateReviews": "Dupliquer les avis",
    "deleteAllReviews": "Supprimer tous les avis",
    "cannotBeUndone": "Cela ne peut pas être annulé.",
    "productGoogleShopInfo": "Informations sur la boutique Google produit",
    "productUrl": "URL du produit",
    "gtins": "RAGS",
    "skus": "SKUs",
    "asins": "ASINs",
    "productTitle": "Titre du produit",
    "mpns": "MPNs",
    "brands": "Marques",
    "downloadXml": "Télécharger XML",
    "reviewsImportedSuccess": "Avis importés avec succès.",
    "reviewsImportedSuccessToast": "Avis importés avec succès.",
    "productNoReviews": "Ce produit n'a pas de commentaires.",
    "errorExportGoogleFeed": "Erreur lors de l'exportation du flux Google",
    "googleFeedExportedSuccess": "Google Feed XML exporté avec succès !",
    "googleFeedExportedToast": "Google Feed XML exporté avec succès !",
    "noReviewsDataToExport": "Aucune donnée de commentaire à exporter",
    "noReviewsDataToExportToast": "Aucune donnée de commentaire à exporter.",
    "tabAll": "Tous",
    "tabShowReviews": "Afficher les avis",
    "tabHideReviews": "Cacher les avis",
    "tabHasReviews": "A des avis",
    "tabHasQuestions": "A des questions",
    "searchPlaceholder": "Recherche dans tous les",
    "searchingInAll": "Recherche dans tous les",
    "exportSuccessToast": "Exportation réussie.",
    "productSavedToast": "Produit enregistré.",
    "reviewsDeletedToast": "Avis supprimés.",
    "productsSavedToast": "Produits enregistrés.",
    "noProductsSelectedToast": "Aucun produit sélectionné.",
    "cantExportToast": "Impossible d'exporter les commentaires.",
    "bulkDeleteTitle": "Supprimer tous les avis sur les produits {{count}}",
    "aToZ": "A à Z",
    "zToA": "Z-A",
    "show": "Afficher",
    "hide": "Cacher",
    "viewProductTooltip": "Voir le produit sur votre boutique",
    "createdAt": "Créé le",
    "product": "Produit",
    "products": "produits",
    "exportCsv": "Exporter CSV",
    "exportGoogleFeed": "Exporter le flux Google",
    "reviewsCopiedSuccess": "Avis copiés avec succès.",
    "failedToCopyReviews": "Impossible de copier les avis : ",
    "copyReviewsError": "Erreur lors de la copie des commentaires.",
    "copyReviews": "Copier les commentaires",
    "chromeRequired": "Navigateur Chrome requis",
    "chromeRequiredDescription": "La fonction d'avis d'importation nécessite le navigateur Chrome pour fonctionner correctement. Veuillez passer à Chrome pour utiliser cette fonctionnalité.",
    "chromeRequiredTooltip": "Ne prend en charge que le navigateur Chrome"
  },
  "copyReviewsModal": {
    "from": "A partir de",
    "to": "À",
    "searchProductsPlaceholder": "Rechercher des produits...",
    "searchingProducts": "Recherche de produits...",
    "noProductsFound": "Aucun produit trouvé.",
    "reviews": "avis"
  },
  "importSettings": {
    "generalDescription": "Gérer les paramètres généraux pour l'importation des commentaires de produits.",
    "removeDuplicateReviews": "Supprimer les avis dupliqués",
    "importImageReviewsOnly": "Importer uniquement les revues d'images",
    "reviewQuantityPerImport": "Revoir la quantité par import",
    "optionForAliexpress": "Option pour Aliexpress",
    "optionForAliexpressDesc": "Personnalisez comment les avis d'Aliexpress sont importés.",
    "translateReviews": "Traduire les avis",
    "optionForAmazon": "Option pour Amazon",
    "optionForAmazonDesc": "Activer ou désactiver l'importation des avis produits par ASIN depuis Amazon.",
    "importByASIN": "Importer par ASIN",
    "syncNewReviews": "Synchroniser les nouveaux avis",
    "syncNewReviewsDesc": "Définir la période de mise à jour des nouveaux commentaires.",
    "updateReviewsInDateRange": "Mettre à jour les commentaires dans la plage de dates",
    "last7Days": "Les 7 derniers jours",
    "last30Days": "Les 30 derniers jours",
    "last90Days": "Les 90 derniers jours",
    "last180Days": "Les 180 derniers jours",
    "last365Days": "365 derniers jours",
    "filterByCountry": "Filtrer par pays"
  }
}